{"v":"4.8.0","meta":{"g":"LottieFiles AE 2.0.4","a":"","k":"","d":"","tc":""},"fr":29.9700012207031,"ip":0,"op":189.000007698128,"w":1080,"h":1080,"nm":"6. Dolphin","ddd":0,"assets":[],"layers":[{"ddd":0,"ind":1,"ty":4,"nm":"Eye","parent":4,"sr":1,"ks":{"o":{"a":0,"k":100,"ix":11},"r":{"a":0,"k":0,"ix":10},"p":{"a":0,"k":[-137.303,-16.642,0],"ix":2},"a":{"a":0,"k":[-137.303,-16.642,0],"ix":1},"s":{"a":1,"k":[{"i":{"x":[0.667,0.667,0.667],"y":[1,1,1]},"o":{"x":[0.167,0.167,0.167],"y":[0,0,0]},"t":0,"s":[100,100,100]},{"i":{"x":[0.833,0.833,0.833],"y":[1,1,1]},"o":{"x":[0.167,0.167,0.167],"y":[0,0.167,0]},"t":16,"s":[100,100,100]},{"i":{"x":[0.833,0.833,0.833],"y":[1,0.833,1]},"o":{"x":[0.167,0.167,0.167],"y":[0,0,0]},"t":23,"s":[100,0,100]},{"i":{"x":[0.833,0.833,0.833],"y":[1,1,1]},"o":{"x":[0.333,0.333,0.333],"y":[0,0,0]},"t":30,"s":[100,100,100]},{"t":64.0000026067734,"s":[100,100,100]}],"ix":6,"x":"var $bm_rt;\n$bm_rt = loopOut();"}},"ao":0,"ef":[{"ty":28,"nm":"Set Matte","np":8,"mn":"ADBE Set Matte3","ix":1,"en":1,"ef":[{"ty":10,"nm":"Take Matte From Layer","mn":"ADBE Set Matte3-0001","ix":1,"v":{"a":0,"k":7,"ix":1}},{"ty":7,"nm":"Use For Matte","mn":"ADBE Set Matte3-0002","ix":2,"v":{"a":0,"k":4,"ix":2}},{"ty":7,"nm":"Invert Matte","mn":"ADBE Set Matte3-0003","ix":3,"v":{"a":0,"k":0,"ix":3}},{"ty":7,"nm":"If Layer Sizes Differ","mn":"ADBE Set Matte3-0004","ix":4,"v":{"a":0,"k":1,"ix":4}},{"ty":7,"nm":"Composite Matte with Original","mn":"ADBE Set Matte3-0005","ix":5,"v":{"a":0,"k":1,"ix":5}},{"ty":7,"nm":"Premultiply Matte Layer","mn":"ADBE Set Matte3-0006","ix":6,"v":{"a":0,"k":1,"ix":6}}]}],"shapes":[{"ty":"gr","it":[{"ty":"gr","it":[{"ty":"gr","it":[{"ind":0,"ty":"sh","ix":1,"ks":{"a":0,"k":{"i":[[0,-2.2],[2.2,0],[0,2.2],[-2.2,0]],"o":[[0,2.2],[-2.2,0],[0,-2.2],[2.2,0]],"v":[[-133.614,-16.643],[-137.598,-12.659],[-141.581,-16.643],[-137.598,-20.626]],"c":true},"ix":2},"nm":"Path 1","mn":"ADBE Vector Shape - Group","hd":false},{"ty":"fl","c":{"a":0,"k":[0.137254908681,0.121568627656,0.1254902035,1],"ix":4},"o":{"a":0,"k":100,"ix":5},"r":1,"bm":0,"nm":"Fill 1","mn":"ADBE Vector Graphic - Fill","hd":false},{"ty":"tr","p":{"a":0,"k":[0,0],"ix":2},"a":{"a":0,"k":[0,0],"ix":1},"s":{"a":0,"k":[100,100],"ix":3},"r":{"a":0,"k":0,"ix":6},"o":{"a":0,"k":100,"ix":7},"sk":{"a":0,"k":0,"ix":4},"sa":{"a":0,"k":0,"ix":5},"nm":"Transform"}],"nm":"Group 1","np":2,"cix":2,"bm":0,"ix":1,"mn":"ADBE Vector Group","hd":false},{"ty":"gr","it":[{"ind":0,"ty":"sh","ix":1,"ks":{"a":0,"k":{"i":[[0,-2.575],[2.575,0],[0,2.576],[-2.575,0]],"o":[[0,2.576],[-2.575,0],[0,-2.575],[2.575,0]],"v":[[-132.388,-16.643],[-137.555,-11.98],[-142.218,-16.643],[-137.555,-21.305]],"c":true},"ix":2},"nm":"Path 1","mn":"ADBE Vector Shape - Group","hd":false},{"ty":"fl","c":{"a":0,"k":[0,0,0,1],"ix":4},"o":{"a":0,"k":100,"ix":5},"r":1,"bm":0,"nm":"Fill 1","mn":"ADBE Vector Graphic - Fill","hd":false},{"ty":"tr","p":{"a":0,"k":[0,0],"ix":2},"a":{"a":0,"k":[0,0],"ix":1},"s":{"a":0,"k":[100,100],"ix":3},"r":{"a":0,"k":0,"ix":6},"o":{"a":0,"k":10,"ix":7},"sk":{"a":0,"k":0,"ix":4},"sa":{"a":0,"k":0,"ix":5},"nm":"Transform"}],"nm":"Group 2","np":2,"cix":2,"bm":0,"ix":2,"mn":"ADBE Vector Group","hd":false},{"ty":"tr","p":{"a":0,"k":[0,0],"ix":2},"a":{"a":0,"k":[0,0],"ix":1},"s":{"a":0,"k":[100,100],"ix":3},"r":{"a":0,"k":0,"ix":6},"o":{"a":0,"k":100,"ix":7},"sk":{"a":0,"k":0,"ix":4},"sa":{"a":0,"k":0,"ix":5},"nm":"Transform"}],"nm":"Eye","np":2,"cix":2,"bm":0,"ix":1,"mn":"ADBE Vector Group","hd":false},{"ty":"tr","p":{"a":0,"k":[0,0],"ix":2},"a":{"a":0,"k":[0,0],"ix":1},"s":{"a":0,"k":[100,100],"ix":3},"r":{"a":0,"k":0,"ix":6},"o":{"a":0,"k":100,"ix":7},"sk":{"a":0,"k":0,"ix":4},"sa":{"a":0,"k":0,"ix":5},"nm":"Transform"}],"nm":"Dolphin","np":1,"cix":2,"bm":0,"ix":1,"mn":"ADBE Vector Group","hd":false}],"ip":0,"op":565.000023012922,"st":0,"bm":0},{"ddd":0,"ind":2,"ty":4,"nm":"Fin 1","parent":4,"sr":1,"ks":{"o":{"a":0,"k":100,"ix":11},"r":{"a":1,"k":[{"i":{"x":[0.667],"y":[1]},"o":{"x":[0.167],"y":[0]},"t":0,"s":[4]},{"i":{"x":[0.833],"y":[1]},"o":{"x":[0.167],"y":[0]},"t":45,"s":[4]},{"i":{"x":[0.667],"y":[1]},"o":{"x":[0.333],"y":[0]},"t":55,"s":[-2]},{"i":{"x":[0.667],"y":[1]},"o":{"x":[0.167],"y":[0]},"t":65,"s":[4]},{"i":{"x":[0.667],"y":[1]},"o":{"x":[0.333],"y":[0]},"t":75,"s":[-2]},{"i":{"x":[0.667],"y":[1]},"o":{"x":[0.167],"y":[0]},"t":85,"s":[4]},{"t":94.0000038286985,"s":[4]}],"ix":10,"x":"var $bm_rt;\n$bm_rt = loopOut();"},"p":{"a":0,"k":[-56.202,-15.162,0],"ix":2},"a":{"a":0,"k":[-56.202,-15.162,0],"ix":1},"s":{"a":0,"k":[100,100,100],"ix":6}},"ao":0,"ef":[{"ty":28,"nm":"Set Matte","np":8,"mn":"ADBE Set Matte3","ix":1,"en":1,"ef":[{"ty":10,"nm":"Take Matte From Layer","mn":"ADBE Set Matte3-0001","ix":1,"v":{"a":0,"k":7,"ix":1}},{"ty":7,"nm":"Use For Matte","mn":"ADBE Set Matte3-0002","ix":2,"v":{"a":0,"k":4,"ix":2}},{"ty":7,"nm":"Invert Matte","mn":"ADBE Set Matte3-0003","ix":3,"v":{"a":0,"k":0,"ix":3}},{"ty":7,"nm":"If Layer Sizes Differ","mn":"ADBE Set Matte3-0004","ix":4,"v":{"a":0,"k":1,"ix":4}},{"ty":7,"nm":"Composite Matte with Original","mn":"ADBE Set Matte3-0005","ix":5,"v":{"a":0,"k":1,"ix":5}},{"ty":7,"nm":"Premultiply Matte Layer","mn":"ADBE Set Matte3-0006","ix":6,"v":{"a":0,"k":1,"ix":6}}]}],"shapes":[{"ty":"gr","it":[{"ty":"gr","it":[{"ty":"gr","it":[{"ind":0,"ty":"sh","ix":1,"ks":{"a":0,"k":{"i":[[0.626,-8.446],[-7.195,-5.005],[-15.328,-3.129],[0.313,3.675],[4.379,6.256],[11.887,0.626]],"o":[[-0.531,7.175],[7.195,5.004],[15.328,3.128],[-0.312,-3.676],[-4.379,-6.256],[-11.887,-0.626]],"v":[[-58.591,-13.71],[-43.263,-1.823],[-7.916,16.008],[9.289,14.131],[-8.228,-11.208],[-30.125,-23.72]],"c":true},"ix":2},"nm":"Path 1","mn":"ADBE Vector Shape - Group","hd":false},{"ty":"fl","c":{"a":0,"k":[0.427450984716,0.505882382393,0.549019634724,1],"ix":4},"o":{"a":0,"k":100,"ix":5},"r":1,"bm":0,"nm":"Fill 1","mn":"ADBE Vector Graphic - Fill","hd":false},{"ty":"tr","p":{"a":0,"k":[0,0],"ix":2},"a":{"a":0,"k":[0,0],"ix":1},"s":{"a":0,"k":[100,100],"ix":3},"r":{"a":0,"k":0,"ix":6},"o":{"a":0,"k":100,"ix":7},"sk":{"a":0,"k":0,"ix":4},"sa":{"a":0,"k":0,"ix":5},"nm":"Transform"}],"nm":"Group 1","np":2,"cix":2,"bm":0,"ix":1,"mn":"ADBE Vector Group","hd":false},{"ty":"gr","it":[{"ind":0,"ty":"sh","ix":1,"ks":{"a":0,"k":{"i":[[0.626,-8.446],[-7.195,-5.005],[-15.328,-3.129],[0.313,3.675],[4.379,6.256],[11.887,0.626]],"o":[[-0.531,7.175],[7.195,5.004],[15.328,3.128],[-0.312,-3.676],[-4.379,-6.256],[-11.887,-0.626]],"v":[[-59.591,-12.71],[-44.263,-0.823],[-8.916,17.008],[8.289,15.131],[-9.228,-10.208],[-31.125,-22.72]],"c":true},"ix":2},"nm":"Path 1","mn":"ADBE Vector Shape - Group","hd":false},{"ty":"fl","c":{"a":0,"k":[0.364705890417,0.40000000596,0.407843142748,1],"ix":4},"o":{"a":0,"k":100,"ix":5},"r":1,"bm":0,"nm":"Fill 1","mn":"ADBE Vector Graphic - Fill","hd":false},{"ty":"tr","p":{"a":0,"k":[0,0],"ix":2},"a":{"a":0,"k":[0,0],"ix":1},"s":{"a":0,"k":[100,100],"ix":3},"r":{"a":0,"k":0,"ix":6},"o":{"a":0,"k":100,"ix":7},"sk":{"a":0,"k":0,"ix":4},"sa":{"a":0,"k":0,"ix":5},"nm":"Transform"}],"nm":"Group 2","np":2,"cix":2,"bm":0,"ix":2,"mn":"ADBE Vector Group","hd":false},{"ty":"tr","p":{"a":0,"k":[0,0],"ix":2},"a":{"a":0,"k":[0,0],"ix":1},"s":{"a":0,"k":[100,100],"ix":3},"r":{"a":0,"k":0,"ix":6},"o":{"a":0,"k":100,"ix":7},"sk":{"a":0,"k":0,"ix":4},"sa":{"a":0,"k":0,"ix":5},"nm":"Transform"}],"nm":"Fin 1","np":2,"cix":2,"bm":0,"ix":1,"mn":"ADBE Vector Group","hd":false},{"ty":"tr","p":{"a":0,"k":[0,0],"ix":2},"a":{"a":0,"k":[0,0],"ix":1},"s":{"a":0,"k":[100,100],"ix":3},"r":{"a":0,"k":0,"ix":6},"o":{"a":0,"k":100,"ix":7},"sk":{"a":0,"k":0,"ix":4},"sa":{"a":0,"k":0,"ix":5},"nm":"Transform"}],"nm":"Dolphin","np":1,"cix":2,"bm":0,"ix":1,"mn":"ADBE Vector Group","hd":false}],"ip":0,"op":565.000023012922,"st":0,"bm":0},{"ddd":0,"ind":3,"ty":4,"nm":"Body","parent":4,"sr":1,"ks":{"o":{"a":0,"k":100,"ix":11},"r":{"a":1,"k":[{"i":{"x":[0.667],"y":[1]},"o":{"x":[0.167],"y":[0]},"t":0,"s":[4]},{"i":{"x":[0.833],"y":[1]},"o":{"x":[0.167],"y":[0]},"t":45,"s":[4]},{"i":{"x":[0.667],"y":[1]},"o":{"x":[0.333],"y":[0]},"t":55,"s":[-2]},{"i":{"x":[0.667],"y":[1]},"o":{"x":[0.167],"y":[0]},"t":65,"s":[4]},{"i":{"x":[0.667],"y":[1]},"o":{"x":[0.333],"y":[0]},"t":75,"s":[-2]},{"i":{"x":[0.667],"y":[1]},"o":{"x":[0.167],"y":[0]},"t":85,"s":[4]},{"t":94.0000038286985,"s":[4]}],"ix":10,"x":"var $bm_rt;\n$bm_rt = loopOut();"},"p":{"a":0,"k":[27.214,-33.706,0],"ix":2},"a":{"a":0,"k":[27.214,-33.706,0],"ix":1},"s":{"a":0,"k":[100,100,100],"ix":6}},"ao":0,"ef":[{"ty":28,"nm":"Set Matte","np":8,"mn":"ADBE Set Matte3","ix":1,"en":1,"ef":[{"ty":10,"nm":"Take Matte From Layer","mn":"ADBE Set Matte3-0001","ix":1,"v":{"a":0,"k":7,"ix":1}},{"ty":7,"nm":"Use For Matte","mn":"ADBE Set Matte3-0002","ix":2,"v":{"a":0,"k":4,"ix":2}},{"ty":7,"nm":"Invert Matte","mn":"ADBE Set Matte3-0003","ix":3,"v":{"a":0,"k":0,"ix":3}},{"ty":7,"nm":"If Layer Sizes Differ","mn":"ADBE Set Matte3-0004","ix":4,"v":{"a":0,"k":1,"ix":4}},{"ty":7,"nm":"Composite Matte with Original","mn":"ADBE Set Matte3-0005","ix":5,"v":{"a":0,"k":1,"ix":5}},{"ty":7,"nm":"Premultiply Matte Layer","mn":"ADBE Set Matte3-0006","ix":6,"v":{"a":0,"k":1,"ix":6}}]}],"shapes":[{"ty":"gr","it":[{"ty":"gr","it":[{"ty":"gr","it":[{"ind":0,"ty":"sh","ix":1,"ks":{"a":0,"k":{"i":[[0,0],[0,0],[-42.465,-12.434],[-7.742,-8.915],[-0.543,-1.455],[0,0],[0,0],[1.554,1.789],[42.464,12.435],[0,0],[2.254,0.251],[0,0],[0,0]],"o":[[16.537,1.708],[0,0],[42.464,12.435],[0.374,0.431],[0,0],[0,0],[0.097,-3.519],[-7.742,-8.915],[-42.465,-12.435],[0,0],[0,0],[0,0],[0,0]],"v":[[-20.689,7.254],[8.977,10.455],[53.787,22.654],[117.366,67.23],[119.108,70.088],[119.228,70.253],[119.23,70.18],[116.54,62.336],[53.787,17.285],[8.977,5.086],[5.232,4.454],[1.875,4.294],[-20.717,1.977]],"c":true},"ix":2},"nm":"Path 1","mn":"ADBE Vector Shape - Group","hd":false},{"ty":"fl","c":{"a":0,"k":[0,0,0,1],"ix":4},"o":{"a":0,"k":100,"ix":5},"r":1,"bm":0,"nm":"Fill 1","mn":"ADBE Vector Graphic - Fill","hd":false},{"ty":"tr","p":{"a":0,"k":[0,0],"ix":2},"a":{"a":0,"k":[0,0],"ix":1},"s":{"a":0,"k":[100,100],"ix":3},"r":{"a":0,"k":0,"ix":6},"o":{"a":0,"k":10,"ix":7},"sk":{"a":0,"k":0,"ix":4},"sa":{"a":0,"k":0,"ix":5},"nm":"Transform"}],"nm":"Group 1","np":2,"cix":2,"bm":0,"ix":1,"mn":"ADBE Vector Group","hd":false},{"ty":"gr","it":[{"ind":0,"ty":"sh","ix":1,"ks":{"a":0,"k":{"i":[[23.034,31.106],[15.435,10.595],[-67.137,-24.371],[-22.119,-6.477],[-7.742,-8.915],[-0.344,-0.949],[3.163,19.183]],"o":[[-16.355,-22.085],[-60.207,-32.116],[5.687,1.426],[42.464,12.435],[0.83,0.955],[9.902,13.697],[-6.204,-15.959]],"v":[[105.167,-22.625],[50.714,-72.65],[14.746,11.713],[53.787,22.654],[117.366,67.23],[119.108,70.088],[147.463,59.281]],"c":true},"ix":2},"nm":"Path 1","mn":"ADBE Vector Shape - Group","hd":false},{"ty":"fl","c":{"a":0,"k":[0.427450984716,0.505882382393,0.549019634724,1],"ix":4},"o":{"a":0,"k":100,"ix":5},"r":1,"bm":0,"nm":"Fill 1","mn":"ADBE Vector Graphic - Fill","hd":false},{"ty":"tr","p":{"a":0,"k":[0,0],"ix":2},"a":{"a":0,"k":[0,0],"ix":1},"s":{"a":0,"k":[100,100],"ix":3},"r":{"a":0,"k":0,"ix":6},"o":{"a":0,"k":100,"ix":7},"sk":{"a":0,"k":0,"ix":4},"sa":{"a":0,"k":0,"ix":5},"nm":"Transform"}],"nm":"Group 2","np":2,"cix":2,"bm":0,"ix":2,"mn":"ADBE Vector Group","hd":false},{"ty":"tr","p":{"a":0,"k":[0,0],"ix":2},"a":{"a":0,"k":[0,0],"ix":1},"s":{"a":0,"k":[100,100],"ix":3},"r":{"a":0,"k":0,"ix":6},"o":{"a":0,"k":100,"ix":7},"sk":{"a":0,"k":0,"ix":4},"sa":{"a":0,"k":0,"ix":5},"nm":"Transform"}],"nm":"Body 2","np":2,"cix":2,"bm":0,"ix":1,"mn":"ADBE Vector Group","hd":false},{"ty":"tr","p":{"a":0,"k":[0,0],"ix":2},"a":{"a":0,"k":[0,0],"ix":1},"s":{"a":0,"k":[100,100],"ix":3},"r":{"a":0,"k":0,"ix":6},"o":{"a":0,"k":100,"ix":7},"sk":{"a":0,"k":0,"ix":4},"sa":{"a":0,"k":0,"ix":5},"nm":"Transform"}],"nm":"Dolphin","np":1,"cix":2,"bm":0,"ix":1,"mn":"ADBE Vector Group","hd":false}],"ip":0,"op":565.000023012922,"st":0,"bm":0},{"ddd":0,"ind":4,"ty":4,"nm":"Head","sr":1,"ks":{"o":{"a":0,"k":100,"ix":11},"r":{"a":1,"k":[{"i":{"x":[0.833],"y":[1]},"o":{"x":[0.333],"y":[0]},"t":0,"s":[0]},{"i":{"x":[0.667],"y":[1]},"o":{"x":[0.333],"y":[0]},"t":24,"s":[0]},{"i":{"x":[0.667],"y":[1]},"o":{"x":[0.167],"y":[0]},"t":55,"s":[-360]},{"t":94.0000038286985,"s":[-360]}],"ix":10,"x":"var $bm_rt;\n$bm_rt = loopOut();"},"p":{"a":1,"k":[{"i":{"x":0.833,"y":0.668},"o":{"x":0.167,"y":0.167},"t":0,"s":[532.926,906.189,0],"to":[0,-0.029,0],"ti":[0,0.117,0]},{"i":{"x":0.833,"y":0.779},"o":{"x":0.167,"y":0.111},"t":1,"s":[532.926,906.014,0],"to":[0,-0.117,0],"ti":[0,0.232,0]},{"i":{"x":0.833,"y":0.801},"o":{"x":0.167,"y":0.134},"t":2,"s":[532.926,905.49,0],"to":[0,-0.232,0],"ti":[0,0.345,0]},{"i":{"x":0.833,"y":0.811},"o":{"x":0.167,"y":0.143},"t":3,"s":[532.926,904.623,0],"to":[0,-0.345,0],"ti":[0,0.454,0]},{"i":{"x":0.833,"y":0.817},"o":{"x":0.167,"y":0.149},"t":4,"s":[532.926,903.421,0],"to":[0,-0.454,0],"ti":[0,0.559,0]},{"i":{"x":0.833,"y":0.82},"o":{"x":0.167,"y":0.153},"t":5,"s":[532.926,901.896,0],"to":[0,-0.559,0],"ti":[0,0.659,0]},{"i":{"x":0.833,"y":0.823},"o":{"x":0.167,"y":0.155},"t":6,"s":[532.926,900.064,0],"to":[0,-0.659,0],"ti":[0,0.752,0]},{"i":{"x":0.833,"y":0.825},"o":{"x":0.167,"y":0.157},"t":7,"s":[532.926,897.943,0],"to":[0,-0.752,0],"ti":[0,0.837,0]},{"i":{"x":0.833,"y":0.826},"o":{"x":0.167,"y":0.159},"t":8,"s":[532.926,895.554,0],"to":[0,-0.837,0],"ti":[0,0.914,0]},{"i":{"x":0.833,"y":0.828},"o":{"x":0.167,"y":0.16},"t":9,"s":[532.926,892.921,0],"to":[0,-0.914,0],"ti":[0,0.982,0]},{"i":{"x":0.833,"y":0.829},"o":{"x":0.167,"y":0.161},"t":10,"s":[532.926,890.07,0],"to":[0,-0.982,0],"ti":[0,1.04,0]},{"i":{"x":0.833,"y":0.83},"o":{"x":0.167,"y":0.163},"t":11,"s":[532.926,887.031,0],"to":[0,-1.04,0],"ti":[0,1.087,0]},{"i":{"x":0.833,"y":0.831},"o":{"x":0.167,"y":0.163},"t":12,"s":[532.926,883.832,0],"to":[0,-1.087,0],"ti":[0,1.124,0]},{"i":{"x":0.833,"y":0.832},"o":{"x":0.167,"y":0.164},"t":13,"s":[532.926,880.508,0],"to":[0,-1.124,0],"ti":[0,1.149,0]},{"i":{"x":0.833,"y":0.833},"o":{"x":0.167,"y":0.165},"t":14,"s":[532.926,877.09,0],"to":[0,-1.149,0],"ti":[0,1.163,0]},{"i":{"x":0.833,"y":0.834},"o":{"x":0.167,"y":0.166},"t":15,"s":[532.926,873.613,0],"to":[0,-1.163,0],"ti":[0,1.165,0]},{"i":{"x":0.833,"y":0.834},"o":{"x":0.167,"y":0.167},"t":16,"s":[532.926,870.111,0],"to":[0,-1.165,0],"ti":[0,1.156,0]},{"i":{"x":0.833,"y":0.835},"o":{"x":0.167,"y":0.168},"t":17,"s":[532.926,866.621,0],"to":[0,-1.156,0],"ti":[0,1.135,0]},{"i":{"x":0.833,"y":0.836},"o":{"x":0.167,"y":0.169},"t":18,"s":[532.926,863.176,0],"to":[0,-1.135,0],"ti":[0,1.103,0]},{"i":{"x":0.833,"y":0.837},"o":{"x":0.167,"y":0.17},"t":19,"s":[532.926,859.811,0],"to":[0,-1.103,0],"ti":[0,1.059,0]},{"i":{"x":0.833,"y":0.838},"o":{"x":0.167,"y":0.171},"t":20,"s":[532.926,856.56,0],"to":[0,-1.059,0],"ti":[0,1.005,0]},{"i":{"x":0.833,"y":0.839},"o":{"x":0.167,"y":0.172},"t":21,"s":[532.926,853.456,0],"to":[0,-1.005,0],"ti":[0,0.941,0]},{"i":{"x":0.833,"y":0.841},"o":{"x":0.167,"y":0.173},"t":22,"s":[532.926,850.529,0],"to":[0,-0.941,0],"ti":[0,0.868,0]},{"i":{"x":0.833,"y":0.842},"o":{"x":0.167,"y":0.175},"t":23,"s":[532.926,847.809,0],"to":[0,-0.868,0],"ti":[0,0.785,0]},{"i":{"x":0.833,"y":0.844},"o":{"x":0.167,"y":0.176},"t":24,"s":[532.926,845.324,0],"to":[0,-0.785,0],"ti":[0,0.695,0]},{"i":{"x":0.833,"y":0.846},"o":{"x":0.167,"y":0.179},"t":25,"s":[532.926,843.097,0],"to":[0,-0.695,0],"ti":[0,0.598,0]},{"i":{"x":0.833,"y":0.849},"o":{"x":0.167,"y":0.182},"t":26,"s":[532.926,841.151,0],"to":[0,-0.598,0],"ti":[0,0.495,0]},{"i":{"x":0.833,"y":0.854},"o":{"x":0.167,"y":0.187},"t":27,"s":[532.926,839.506,0],"to":[0,-0.495,0],"ti":[0,0.387,0]},{"i":{"x":0.833,"y":0.862},"o":{"x":0.167,"y":0.194},"t":28,"s":[532.926,838.179,0],"to":[0,-0.387,0],"ti":[0,0.276,0]},{"i":{"x":0.833,"y":0.877},"o":{"x":0.167,"y":0.21},"t":29,"s":[532.926,837.181,0],"to":[0,-0.276,0],"ti":[0,0.161,0]},{"i":{"x":0.833,"y":0.892},"o":{"x":0.167,"y":0.26},"t":30,"s":[532.926,836.525,0],"to":[0,-0.161,0],"ti":[0,0.045,0]},{"i":{"x":0.833,"y":0.565},"o":{"x":0.167,"y":0.362},"t":31,"s":[532.926,836.215,0],"to":[0,-0.045,0],"ti":[0,-0.072,0]},{"i":{"x":0.833,"y":0.759},"o":{"x":0.167,"y":0.103},"t":32,"s":[532.926,836.256,0],"to":[0,0.072,0],"ti":[0,-0.188,0]},{"i":{"x":0.833,"y":0.795},"o":{"x":0.167,"y":0.128},"t":33,"s":[532.926,836.646,0],"to":[0,0.188,0],"ti":[0,-0.302,0]},{"i":{"x":0.833,"y":0.808},"o":{"x":0.167,"y":0.14},"t":34,"s":[532.926,837.382,0],"to":[0,0.302,0],"ti":[0,-0.413,0]},{"i":{"x":0.833,"y":0.815},"o":{"x":0.167,"y":0.147},"t":35,"s":[532.926,838.456,0],"to":[0,0.413,0],"ti":[0,-0.52,0]},{"i":{"x":0.833,"y":0.819},"o":{"x":0.167,"y":0.151},"t":36,"s":[532.926,839.859,0],"to":[0,0.52,0],"ti":[0,-0.621,0]},{"i":{"x":0.833,"y":0.822},"o":{"x":0.167,"y":0.154},"t":37,"s":[532.926,841.575,0],"to":[0,0.621,0],"ti":[0,-0.717,0]},{"i":{"x":0.833,"y":0.824},"o":{"x":0.167,"y":0.157},"t":38,"s":[532.926,843.587,0],"to":[0,0.717,0],"ti":[0,-0.805,0]},{"i":{"x":0.833,"y":0.826},"o":{"x":0.167,"y":0.158},"t":39,"s":[532.926,845.876,0],"to":[0,0.805,0],"ti":[0,-0.885,0]},{"i":{"x":0.833,"y":0.827},"o":{"x":0.167,"y":0.16},"t":40,"s":[532.926,848.418,0],"to":[0,0.885,0],"ti":[0,-0.957,0]},{"i":{"x":0.833,"y":0.829},"o":{"x":0.167,"y":0.161},"t":41,"s":[532.926,851.188,0],"to":[0,0.957,0],"ti":[0,-1.019,0]},{"i":{"x":0.833,"y":0.83},"o":{"x":0.167,"y":0.162},"t":42,"s":[532.926,854.158,0],"to":[0,1.019,0],"ti":[0,-1.07,0]},{"i":{"x":0.833,"y":0.831},"o":{"x":0.167,"y":0.163},"t":43,"s":[532.926,857.299,0],"to":[0,1.07,0],"ti":[0,-1.111,0]},{"i":{"x":0.833,"y":0.832},"o":{"x":0.167,"y":0.164},"t":44,"s":[532.926,860.579,0],"to":[0,1.111,0],"ti":[0,-1.141,0]},{"i":{"x":0.833,"y":0.832},"o":{"x":0.167,"y":0.165},"t":45,"s":[532.926,863.965,0],"to":[0,1.141,0],"ti":[0,-1.159,0]},{"i":{"x":0.833,"y":0.833},"o":{"x":0.167,"y":0.166},"t":46,"s":[532.926,867.424,0],"to":[0,1.159,0],"ti":[0,-1.166,0]},{"i":{"x":0.833,"y":0.834},"o":{"x":0.167,"y":0.167},"t":47,"s":[532.926,870.92,0],"to":[0,1.166,0],"ti":[0,-1.161,0]},{"i":{"x":0.833,"y":0.835},"o":{"x":0.167,"y":0.167},"t":48,"s":[532.926,874.419,0],"to":[0,1.161,0],"ti":[0,-1.144,0]},{"i":{"x":0.833,"y":0.836},"o":{"x":0.167,"y":0.168},"t":49,"s":[532.926,877.886,0],"to":[0,1.144,0],"ti":[0,-1.116,0]},{"i":{"x":0.833,"y":0.837},"o":{"x":0.167,"y":0.169},"t":50,"s":[532.926,881.285,0],"to":[0,1.116,0],"ti":[0,-1.077,0]},{"i":{"x":0.833,"y":0.838},"o":{"x":0.167,"y":0.17},"t":51,"s":[532.926,884.584,0],"to":[0,1.077,0],"ti":[0,-1.027,0]},{"i":{"x":0.833,"y":0.839},"o":{"x":0.167,"y":0.171},"t":52,"s":[532.926,887.748,0],"to":[0,1.027,0],"ti":[0,-0.967,0]},{"i":{"x":0.833,"y":0.84},"o":{"x":0.167,"y":0.172},"t":53,"s":[532.926,890.747,0],"to":[0,0.967,0],"ti":[0,-0.897,0]},{"i":{"x":0.833,"y":0.841},"o":{"x":0.167,"y":0.174},"t":54,"s":[532.926,893.549,0],"to":[0,0.897,0],"ti":[0,-0.818,0]},{"i":{"x":0.833,"y":0.843},"o":{"x":0.167,"y":0.176},"t":55,"s":[532.926,896.128,0],"to":[0,0.818,0],"ti":[0,-0.731,0]},{"i":{"x":0.833,"y":0.845},"o":{"x":0.167,"y":0.178},"t":56,"s":[532.926,898.457,0],"to":[0,0.731,0],"ti":[0,-0.636,0]},{"i":{"x":0.833,"y":0.848},"o":{"x":0.167,"y":0.181},"t":57,"s":[532.926,900.514,0],"to":[0,0.636,0],"ti":[0,-0.536,0]},{"i":{"x":0.833,"y":0.852},"o":{"x":0.167,"y":0.185},"t":58,"s":[532.926,902.276,0],"to":[0,0.536,0],"ti":[0,-0.43,0]},{"i":{"x":0.833,"y":0.858},"o":{"x":0.167,"y":0.191},"t":59,"s":[532.926,903.728,0],"to":[0,0.43,0],"ti":[0,-0.319,0]},{"i":{"x":0.833,"y":0.87},"o":{"x":0.167,"y":0.202},"t":60,"s":[532.926,904.853,0],"to":[0,0.319,0],"ti":[0,-0.205,0]},{"i":{"x":0.833,"y":0.895},"o":{"x":0.167,"y":0.231},"t":61,"s":[532.926,905.642,0],"to":[0,0.205,0],"ti":[0,-0.09,0]},{"i":{"x":0.833,"y":0.728},"o":{"x":0.167,"y":0.41},"t":62,"s":[532.926,906.085,0],"to":[0,0.09,0],"ti":[0,0.027,0]},{"i":{"x":0.833,"y":0.72},"o":{"x":0.167,"y":0.12},"t":63,"s":[532.926,906.18,0],"to":[0,-0.027,0],"ti":[0,0.143,0]},{"i":{"x":0.833,"y":0.786},"o":{"x":0.167,"y":0.119},"t":64,"s":[532.926,905.924,0],"to":[0,-0.143,0],"ti":[0,0.258,0]},{"i":{"x":0.833,"y":0.804},"o":{"x":0.167,"y":0.137},"t":65,"s":[532.926,905.32,0],"to":[0,-0.258,0],"ti":[0,0.371,0]},{"i":{"x":0.833,"y":0.812},"o":{"x":0.167,"y":0.145},"t":66,"s":[532.926,904.375,0],"to":[0,-0.371,0],"ti":[0,0.479,0]},{"i":{"x":0.833,"y":0.818},"o":{"x":0.167,"y":0.15},"t":67,"s":[532.926,903.097,0],"to":[0,-0.479,0],"ti":[0,0.583,0]},{"i":{"x":0.833,"y":0.821},"o":{"x":0.167,"y":0.153},"t":68,"s":[532.926,901.5,0],"to":[0,-0.583,0],"ti":[0,0.681,0]},{"i":{"x":0.833,"y":0.823},"o":{"x":0.167,"y":0.156},"t":69,"s":[532.926,899.599,0],"to":[0,-0.681,0],"ti":[0,0.772,0]},{"i":{"x":0.833,"y":0.825},"o":{"x":0.167,"y":0.158},"t":70,"s":[532.926,897.414,0],"to":[0,-0.772,0],"ti":[0,0.856,0]},{"i":{"x":0.833,"y":0.827},"o":{"x":0.167,"y":0.159},"t":71,"s":[532.926,894.966,0],"to":[0,-0.856,0],"ti":[0,0.93,0]},{"i":{"x":0.833,"y":0.828},"o":{"x":0.167,"y":0.161},"t":72,"s":[532.926,892.281,0],"to":[0,-0.93,0],"ti":[0,0.996,0]},{"i":{"x":0.833,"y":0.829},"o":{"x":0.167,"y":0.162},"t":73,"s":[532.926,889.384,0],"to":[0,-0.996,0],"ti":[0,1.052,0]},{"i":{"x":0.833,"y":0.83},"o":{"x":0.167,"y":0.163},"t":74,"s":[532.926,886.305,0],"to":[0,-1.052,0],"ti":[0,1.097,0]},{"i":{"x":0.833,"y":0.831},"o":{"x":0.167,"y":0.164},"t":75,"s":[532.926,883.075,0],"to":[0,-1.097,0],"ti":[0,1.131,0]},{"i":{"x":0.833,"y":0.832},"o":{"x":0.167,"y":0.165},"t":76,"s":[532.926,879.725,0],"to":[0,-1.131,0],"ti":[0,1.153,0]},{"i":{"x":0.833,"y":0.833},"o":{"x":0.167,"y":0.165},"t":77,"s":[532.926,876.29,0],"to":[0,-1.153,0],"ti":[0,1.165,0]},{"i":{"x":0.833,"y":0.834},"o":{"x":0.167,"y":0.166},"t":78,"s":[532.926,872.805,0],"to":[0,-1.165,0],"ti":[0,1.164,0]},{"i":{"x":0.833,"y":0.835},"o":{"x":0.167,"y":0.167},"t":79,"s":[532.926,869.303,0],"to":[0,-1.164,0],"ti":[0,1.152,0]},{"i":{"x":0.833,"y":0.835},"o":{"x":0.167,"y":0.168},"t":80,"s":[532.926,865.82,0],"to":[0,-1.152,0],"ti":[0,1.128,0]},{"i":{"x":0.833,"y":0.836},"o":{"x":0.167,"y":0.169},"t":81,"s":[532.926,862.39,0],"to":[0,-1.128,0],"ti":[0,1.094,0]},{"i":{"x":0.833,"y":0.837},"o":{"x":0.167,"y":0.17},"t":82,"s":[532.926,859.049,0],"to":[0,-1.094,0],"ti":[0,1.048,0]},{"i":{"x":0.833,"y":0.838},"o":{"x":0.167,"y":0.171},"t":83,"s":[532.926,855.829,0],"to":[0,-1.048,0],"ti":[0,0.991,0]},{"i":{"x":0.833,"y":0.84},"o":{"x":0.167,"y":0.172},"t":84,"s":[532.926,852.763,0],"to":[0,-0.991,0],"ti":[0,0.925,0]},{"i":{"x":0.833,"y":0.841},"o":{"x":0.167,"y":0.173},"t":85,"s":[532.926,849.882,0],"to":[0,-0.925,0],"ti":[0,0.849,0]},{"i":{"x":0.833,"y":0.842},"o":{"x":0.167,"y":0.175},"t":86,"s":[532.926,847.214,0],"to":[0,-0.849,0],"ti":[0,0.765,0]},{"i":{"x":0.833,"y":0.844},"o":{"x":0.167,"y":0.177},"t":87,"s":[532.926,844.785,0],"to":[0,-0.765,0],"ti":[0,0.674,0]},{"i":{"x":0.833,"y":0.847},"o":{"x":0.167,"y":0.179},"t":88,"s":[532.926,842.622,0],"to":[0,-0.674,0],"ti":[0,0.575,0]},{"i":{"x":0.833,"y":0.85},"o":{"x":0.167,"y":0.183},"t":89,"s":[532.926,840.744,0],"to":[0,-0.575,0],"ti":[0,0.471,0]},{"i":{"x":0.833,"y":0.855},"o":{"x":0.167,"y":0.188},"t":90,"s":[532.926,839.171,0],"to":[0,-0.471,0],"ti":[0,0.362,0]},{"i":{"x":0.833,"y":0.864},"o":{"x":0.167,"y":0.197},"t":91,"s":[532.926,837.919,0],"to":[0,-0.362,0],"ti":[0,0.249,0]},{"i":{"x":0.833,"y":0.884},"o":{"x":0.167,"y":0.216},"t":92,"s":[532.926,836.999,0],"to":[0,-0.249,0],"ti":[0,0.134,0]},{"i":{"x":0.833,"y":0.869},"o":{"x":0.167,"y":0.293},"t":93,"s":[532.926,836.422,0],"to":[0,-0.134,0],"ti":[0,0.018,0]},{"i":{"x":0.833,"y":0.614},"o":{"x":0.167,"y":0.23},"t":94,"s":[532.926,836.193,0],"to":[0,-0.018,0],"ti":[0,-0.099,0]},{"i":{"x":0.833,"y":0.772},"o":{"x":0.167,"y":0.106},"t":95,"s":[532.926,836.315,0],"to":[0,0.099,0],"ti":[0,-0.214,0]},{"i":{"x":0.833,"y":0.799},"o":{"x":0.167,"y":0.131},"t":96,"s":[532.926,836.785,0],"to":[0,0.214,0],"ti":[0,-0.328,0]},{"i":{"x":0.833,"y":0.81},"o":{"x":0.167,"y":0.142},"t":97,"s":[532.926,837.6,0],"to":[0,0.328,0],"ti":[0,-0.438,0]},{"i":{"x":0.833,"y":0.816},"o":{"x":0.167,"y":0.148},"t":98,"s":[532.926,838.752,0],"to":[0,0.438,0],"ti":[0,-0.544,0]},{"i":{"x":0.833,"y":0.82},"o":{"x":0.167,"y":0.152},"t":99,"s":[532.926,840.228,0],"to":[0,0.544,0],"ti":[0,-0.644,0]},{"i":{"x":0.833,"y":0.822},"o":{"x":0.167,"y":0.155},"t":100,"s":[532.926,842.014,0],"to":[0,0.644,0],"ti":[0,-0.738,0]},{"i":{"x":0.833,"y":0.825},"o":{"x":0.167,"y":0.157},"t":101,"s":[532.926,844.092,0],"to":[0,0.738,0],"ti":[0,-0.824,0]},{"i":{"x":0.833,"y":0.826},"o":{"x":0.167,"y":0.159},"t":102,"s":[532.926,846.441,0],"to":[0,0.824,0],"ti":[0,-0.903,0]},{"i":{"x":0.833,"y":0.828},"o":{"x":0.167,"y":0.16},"t":103,"s":[532.926,849.038,0],"to":[0,0.903,0],"ti":[0,-0.972,0]},{"i":{"x":0.833,"y":0.829},"o":{"x":0.167,"y":0.161},"t":104,"s":[532.926,851.857,0],"to":[0,0.972,0],"ti":[0,-1.031,0]},{"i":{"x":0.833,"y":0.83},"o":{"x":0.167,"y":0.162},"t":105,"s":[532.926,854.87,0],"to":[0,1.031,0],"ti":[0,-1.081,0]},{"i":{"x":0.833,"y":0.831},"o":{"x":0.167,"y":0.163},"t":106,"s":[532.926,858.046,0],"to":[0,1.081,0],"ti":[0,-1.119,0]},{"i":{"x":0.833,"y":0.832},"o":{"x":0.167,"y":0.164},"t":107,"s":[532.926,861.353,0],"to":[0,1.119,0],"ti":[0,-1.146,0]},{"i":{"x":0.833,"y":0.833},"o":{"x":0.167,"y":0.165},"t":108,"s":[532.926,864.759,0],"to":[0,1.146,0],"ti":[0,-1.162,0]},{"i":{"x":0.833,"y":0.833},"o":{"x":0.167,"y":0.166},"t":109,"s":[532.926,868.229,0],"to":[0,1.162,0],"ti":[0,-1.166,0]},{"i":{"x":0.833,"y":0.834},"o":{"x":0.167,"y":0.167},"t":110,"s":[532.926,871.729,0],"to":[0,1.166,0],"ti":[0,-1.158,0]},{"i":{"x":0.833,"y":0.835},"o":{"x":0.167,"y":0.168},"t":111,"s":[532.926,875.224,0],"to":[0,1.158,0],"ti":[0,-1.139,0]},{"i":{"x":0.833,"y":0.836},"o":{"x":0.167,"y":0.169},"t":112,"s":[532.926,878.678,0],"to":[0,1.139,0],"ti":[0,-1.108,0]},{"i":{"x":0.833,"y":0.837},"o":{"x":0.167,"y":0.169},"t":113,"s":[532.926,882.057,0],"to":[0,1.108,0],"ti":[0,-1.067,0]},{"i":{"x":0.833,"y":0.838},"o":{"x":0.167,"y":0.17},"t":114,"s":[532.926,885.328,0],"to":[0,1.067,0],"ti":[0,-1.014,0]},{"i":{"x":0.833,"y":0.839},"o":{"x":0.167,"y":0.172},"t":115,"s":[532.926,888.456,0],"to":[0,1.014,0],"ti":[0,-0.952,0]},{"i":{"x":0.833,"y":0.84},"o":{"x":0.167,"y":0.173},"t":116,"s":[532.926,891.412,0],"to":[0,0.952,0],"ti":[0,-0.879,0]},{"i":{"x":0.833,"y":0.842},"o":{"x":0.167,"y":0.174},"t":117,"s":[532.926,894.166,0],"to":[0,0.879,0],"ti":[0,-0.799,0]},{"i":{"x":0.833,"y":0.844},"o":{"x":0.167,"y":0.176},"t":118,"s":[532.926,896.689,0],"to":[0,0.799,0],"ti":[0,-0.71,0]},{"i":{"x":0.833,"y":0.846},"o":{"x":0.167,"y":0.178},"t":119,"s":[532.926,898.957,0],"to":[0,0.71,0],"ti":[0,-0.614,0]},{"i":{"x":0.833,"y":0.849},"o":{"x":0.167,"y":0.181},"t":120,"s":[532.926,900.947,0],"to":[0,0.614,0],"ti":[0,-0.512,0]},{"i":{"x":0.833,"y":0.853},"o":{"x":0.167,"y":0.186},"t":121,"s":[532.926,902.64,0],"to":[0,0.512,0],"ti":[0,-0.404,0]},{"i":{"x":0.833,"y":0.86},"o":{"x":0.167,"y":0.193},"t":122,"s":[532.926,904.017,0],"to":[0,0.404,0],"ti":[0,-0.293,0]},{"i":{"x":0.833,"y":0.874},"o":{"x":0.167,"y":0.207},"t":123,"s":[532.926,905.066,0],"to":[0,0.293,0],"ti":[0,-0.179,0]},{"i":{"x":0.833,"y":0.896},"o":{"x":0.167,"y":0.246},"t":124,"s":[532.926,905.775,0],"to":[0,0.179,0],"ti":[0,-0.063,0]},{"i":{"x":0.833,"y":0.599},"o":{"x":0.167,"y":0.426},"t":125,"s":[532.926,906.138,0],"to":[0,0.063,0],"ti":[0,0.054,0]},{"i":{"x":0.833,"y":0.748},"o":{"x":0.167,"y":0.105},"t":126,"s":[532.926,906.152,0],"to":[0,-0.054,0],"ti":[0,0.17,0]},{"i":{"x":0.833,"y":0.792},"o":{"x":0.167,"y":0.124},"t":127,"s":[532.926,905.815,0],"to":[0,-0.17,0],"ti":[0,0.284,0]},{"i":{"x":0.833,"y":0.806},"o":{"x":0.167,"y":0.139},"t":128,"s":[532.926,905.132,0],"to":[0,-0.284,0],"ti":[0,0.396,0]},{"i":{"x":0.833,"y":0.814},"o":{"x":0.167,"y":0.146},"t":129,"s":[532.926,904.108,0],"to":[0,-0.396,0],"ti":[0,0.504,0]},{"i":{"x":0.833,"y":0.818},"o":{"x":0.167,"y":0.151},"t":130,"s":[532.926,902.756,0],"to":[0,-0.504,0],"ti":[0,0.606,0]},{"i":{"x":0.833,"y":0.821},"o":{"x":0.167,"y":0.154},"t":131,"s":[532.926,901.087,0],"to":[0,-0.606,0],"ti":[0,0.703,0]},{"i":{"x":0.833,"y":0.824},"o":{"x":0.167,"y":0.156},"t":132,"s":[532.926,899.119,0],"to":[0,-0.703,0],"ti":[0,0.792,0]},{"i":{"x":0.833,"y":0.826},"o":{"x":0.167,"y":0.158},"t":133,"s":[532.926,896.871,0],"to":[0,-0.792,0],"ti":[0,0.874,0]},{"i":{"x":0.833,"y":0.827},"o":{"x":0.167,"y":0.16},"t":134,"s":[532.926,894.366,0],"to":[0,-0.874,0],"ti":[0,0.946,0]},{"i":{"x":0.833,"y":0.828},"o":{"x":0.167,"y":0.161},"t":135,"s":[532.926,891.629,0],"to":[0,-0.946,0],"ti":[0,1.01,0]},{"i":{"x":0.833,"y":0.829},"o":{"x":0.167,"y":0.162},"t":136,"s":[532.926,888.688,0],"to":[0,-1.01,0],"ti":[0,1.063,0]},{"i":{"x":0.833,"y":0.83},"o":{"x":0.167,"y":0.163},"t":137,"s":[532.926,885.571,0],"to":[0,-1.063,0],"ti":[0,1.105,0]},{"i":{"x":0.833,"y":0.831},"o":{"x":0.167,"y":0.164},"t":138,"s":[532.926,882.31,0],"to":[0,-1.105,0],"ti":[0,1.137,0]},{"i":{"x":0.833,"y":0.832},"o":{"x":0.167,"y":0.165},"t":139,"s":[532.926,878.938,0],"to":[0,-1.137,0],"ti":[0,1.157,0]},{"i":{"x":0.833,"y":0.833},"o":{"x":0.167,"y":0.166},"t":140,"s":[532.926,875.489,0],"to":[0,-1.157,0],"ti":[0,1.166,0]},{"i":{"x":0.833,"y":0.834},"o":{"x":0.167,"y":0.166},"t":141,"s":[532.926,871.996,0],"to":[0,-1.166,0],"ti":[0,1.162,0]},{"i":{"x":0.833,"y":0.835},"o":{"x":0.167,"y":0.167},"t":142,"s":[532.926,868.495,0],"to":[0,-1.162,0],"ti":[0,1.148,0]},{"i":{"x":0.833,"y":0.836},"o":{"x":0.167,"y":0.168},"t":143,"s":[532.926,865.021,0],"to":[0,-1.148,0],"ti":[0,1.121,0]},{"i":{"x":0.833,"y":0.837},"o":{"x":0.167,"y":0.169},"t":144,"s":[532.926,861.609,0],"to":[0,-1.121,0],"ti":[0,1.084,0]},{"i":{"x":0.833,"y":0.838},"o":{"x":0.167,"y":0.17},"t":145,"s":[532.926,858.293,0],"to":[0,-1.084,0],"ti":[0,1.036,0]},{"i":{"x":0.833,"y":0.839},"o":{"x":0.167,"y":0.171},"t":146,"s":[532.926,855.106,0],"to":[0,-1.036,0],"ti":[0,0.977,0]},{"i":{"x":0.833,"y":0.84},"o":{"x":0.167,"y":0.172},"t":147,"s":[532.926,852.08,0],"to":[0,-0.977,0],"ti":[0,0.908,0]},{"i":{"x":0.833,"y":0.841},"o":{"x":0.167,"y":0.174},"t":148,"s":[532.926,849.245,0],"to":[0,-0.908,0],"ti":[0,0.831,0]},{"i":{"x":0.833,"y":0.843},"o":{"x":0.167,"y":0.175},"t":149,"s":[532.926,846.63,0],"to":[0,-0.831,0],"ti":[0,0.745,0]},{"i":{"x":0.833,"y":0.845},"o":{"x":0.167,"y":0.177},"t":150,"s":[532.926,844.261,0],"to":[0,-0.745,0],"ti":[0,0.651,0]},{"i":{"x":0.833,"y":0.848},"o":{"x":0.167,"y":0.18},"t":151,"s":[532.926,842.162,0],"to":[0,-0.651,0],"ti":[0,0.552,0]},{"i":{"x":0.833,"y":0.851},"o":{"x":0.167,"y":0.184},"t":152,"s":[532.926,840.353,0],"to":[0,-0.552,0],"ti":[0,0.446,0]},{"i":{"x":0.833,"y":0.857},"o":{"x":0.167,"y":0.19},"t":153,"s":[532.926,838.853,0],"to":[0,-0.446,0],"ti":[0,0.336,0]},{"i":{"x":0.833,"y":0.867},"o":{"x":0.167,"y":0.2},"t":154,"s":[532.926,837.676,0],"to":[0,-0.336,0],"ti":[0,0.223,0]},{"i":{"x":0.833,"y":0.891},"o":{"x":0.167,"y":0.224},"t":155,"s":[532.926,836.835,0],"to":[0,-0.223,0],"ti":[0,0.108,0]},{"i":{"x":0.833,"y":0.804},"o":{"x":0.167,"y":0.359},"t":156,"s":[532.926,836.338,0],"to":[0,-0.108,0],"ti":[0,-0.009,0]},{"i":{"x":0.833,"y":0.69},"o":{"x":0.167,"y":0.145},"t":157,"s":[532.926,836.19,0],"to":[0,0.009,0],"ti":[0,-0.126,0]},{"i":{"x":0.833,"y":0.781},"o":{"x":0.167,"y":0.114},"t":158,"s":[532.926,836.393,0],"to":[0,0.126,0],"ti":[0,-0.241,0]},{"i":{"x":0.833,"y":0.802},"o":{"x":0.167,"y":0.135},"t":159,"s":[532.926,836.943,0],"to":[0,0.241,0],"ti":[0,-0.354,0]},{"i":{"x":0.833,"y":0.811},"o":{"x":0.167,"y":0.144},"t":160,"s":[532.926,837.837,0],"to":[0,0.354,0],"ti":[0,-0.463,0]},{"i":{"x":0.833,"y":0.817},"o":{"x":0.167,"y":0.149},"t":161,"s":[532.926,839.064,0],"to":[0,0.463,0],"ti":[0,-0.567,0]},{"i":{"x":0.833,"y":0.82},"o":{"x":0.167,"y":0.153},"t":162,"s":[532.926,840.613,0],"to":[0,0.567,0],"ti":[0,-0.666,0]},{"i":{"x":0.833,"y":0.823},"o":{"x":0.167,"y":0.155},"t":163,"s":[532.926,842.468,0],"to":[0,0.666,0],"ti":[0,-0.759,0]},{"i":{"x":0.833,"y":0.825},"o":{"x":0.167,"y":0.157},"t":164,"s":[532.926,844.611,0],"to":[0,0.759,0],"ti":[0,-0.843,0]},{"i":{"x":0.833,"y":0.827},"o":{"x":0.167,"y":0.159},"t":165,"s":[532.926,847.02,0],"to":[0,0.843,0],"ti":[0,-0.92,0]},{"i":{"x":0.833,"y":0.828},"o":{"x":0.167,"y":0.16},"t":166,"s":[532.926,849.671,0],"to":[0,0.92,0],"ti":[0,-0.987,0]},{"i":{"x":0.833,"y":0.829},"o":{"x":0.167,"y":0.162},"t":167,"s":[532.926,852.537,0],"to":[0,0.987,0],"ti":[0,-1.044,0]},{"i":{"x":0.833,"y":0.83},"o":{"x":0.167,"y":0.163},"t":168,"s":[532.926,855.59,0],"to":[0,1.044,0],"ti":[0,-1.09,0]},{"i":{"x":0.833,"y":0.831},"o":{"x":0.167,"y":0.164},"t":169,"s":[532.926,858.799,0],"to":[0,1.09,0],"ti":[0,-1.126,0]},{"i":{"x":0.833,"y":0.832},"o":{"x":0.167,"y":0.164},"t":170,"s":[532.926,862.132,0],"to":[0,1.126,0],"ti":[0,-1.151,0]},{"i":{"x":0.833,"y":0.833},"o":{"x":0.167,"y":0.165},"t":171,"s":[532.926,865.556,0],"to":[0,1.151,0],"ti":[0,-1.164,0]},{"i":{"x":0.833,"y":0.834},"o":{"x":0.167,"y":0.166},"t":172,"s":[532.926,869.037,0],"to":[0,1.164,0],"ti":[0,-1.165,0]},{"i":{"x":0.833,"y":0.834},"o":{"x":0.167,"y":0.167},"t":173,"s":[532.926,872.538,0],"to":[0,1.165,0],"ti":[0,-1.155,0]},{"i":{"x":0.833,"y":0.835},"o":{"x":0.167,"y":0.168},"t":174,"s":[532.926,876.027,0],"to":[0,1.155,0],"ti":[0,-1.133,0]},{"i":{"x":0.833,"y":0.836},"o":{"x":0.167,"y":0.169},"t":175,"s":[532.926,879.466,0],"to":[0,1.133,0],"ti":[0,-1.1,0]},{"i":{"x":0.833,"y":0.837},"o":{"x":0.167,"y":0.17},"t":176,"s":[532.926,882.823,0],"to":[0,1.1,0],"ti":[0,-1.055,0]},{"i":{"x":0.833,"y":0.838},"o":{"x":0.167,"y":0.171},"t":177,"s":[532.926,886.064,0],"to":[0,1.055,0],"ti":[0,-1.001,0]},{"i":{"x":0.833,"y":0.839},"o":{"x":0.167,"y":0.172},"t":178,"s":[532.926,889.156,0],"to":[0,1.001,0],"ti":[0,-0.936,0]},{"i":{"x":0.833,"y":0.841},"o":{"x":0.167,"y":0.173},"t":179,"s":[532.926,892.067,0],"to":[0,0.936,0],"ti":[0,-0.862,0]},{"i":{"x":0.833,"y":0.842},"o":{"x":0.167,"y":0.175},"t":180,"s":[532.926,894.77,0],"to":[0,0.862,0],"ti":[0,-0.779,0]},{"i":{"x":0.833,"y":0.844},"o":{"x":0.167,"y":0.177},"t":181,"s":[532.926,897.237,0],"to":[0,0.779,0],"ti":[0,-0.688,0]},{"i":{"x":0.833,"y":0.846},"o":{"x":0.167,"y":0.179},"t":182,"s":[532.926,899.442,0],"to":[0,0.688,0],"ti":[0,-0.591,0]},{"i":{"x":0.833,"y":0.85},"o":{"x":0.167,"y":0.182},"t":183,"s":[532.926,901.365,0],"to":[0,0.591,0],"ti":[0,-0.487,0]},{"i":{"x":0.833,"y":0.855},"o":{"x":0.167,"y":0.187},"t":184,"s":[532.926,902.986,0],"to":[0,0.487,0],"ti":[0,-0.379,0]},{"i":{"x":0.833,"y":0.863},"o":{"x":0.167,"y":0.195},"t":185,"s":[532.926,904.289,0],"to":[0,0.379,0],"ti":[0,-0.267,0]},{"i":{"x":0.833,"y":0.879},"o":{"x":0.167,"y":0.212},"t":186,"s":[532.926,905.26,0],"to":[0,0.267,0],"ti":[0,-0.152,0]},{"i":{"x":0.833,"y":0.887},"o":{"x":0.167,"y":0.269},"t":187,"s":[532.926,905.89,0],"to":[0,0.152,0],"ti":[0,-0.036,0]},{"i":{"x":0.833,"y":0.572},"o":{"x":0.167,"y":0.317},"t":188,"s":[532.926,906.173,0],"to":[0,0.036,0],"ti":[0,0.081,0]},{"i":{"x":0.833,"y":0.764},"o":{"x":0.167,"y":0.103},"t":189,"s":[532.926,906.105,0],"to":[0,-0.081,0],"ti":[0,0.197,0]},{"i":{"x":0.833,"y":0.796},"o":{"x":0.167,"y":0.129},"t":190,"s":[532.926,905.688,0],"to":[0,-0.197,0],"ti":[0,0.31,0]},{"i":{"x":0.833,"y":0.809},"o":{"x":0.167,"y":0.141},"t":191,"s":[532.926,904.925,0],"to":[0,-0.31,0],"ti":[0,0.421,0]},{"i":{"x":0.833,"y":0.815},"o":{"x":0.167,"y":0.148},"t":192,"s":[532.926,903.825,0],"to":[0,-0.421,0],"ti":[0,0.528,0]},{"i":{"x":0.833,"y":0.819},"o":{"x":0.167,"y":0.152},"t":193,"s":[532.926,902.398,0],"to":[0,-0.528,0],"ti":[0,0.629,0]},{"i":{"x":0.833,"y":0.822},"o":{"x":0.167,"y":0.155},"t":194,"s":[532.926,900.658,0],"to":[0,-0.629,0],"ti":[0,0.724,0]},{"i":{"x":0.833,"y":0.824},"o":{"x":0.167,"y":0.157},"t":195,"s":[532.926,898.624,0],"to":[0,-0.724,0],"ti":[0,0.812,0]},{"i":{"x":0.833,"y":0.826},"o":{"x":0.167,"y":0.158},"t":196,"s":[532.926,896.314,0],"to":[0,-0.812,0],"ti":[0,0.891,0]},{"i":{"x":0.833,"y":0.827},"o":{"x":0.167,"y":0.16},"t":197,"s":[532.926,893.754,0],"to":[0,-0.891,0],"ti":[0,0.962,0]},{"i":{"x":0.833,"y":0.829},"o":{"x":0.167,"y":0.161},"t":198,"s":[532.926,890.967,0],"to":[0,-0.962,0],"ti":[0,1.023,0]},{"i":{"x":0.833,"y":0.83},"o":{"x":0.167,"y":0.162},"t":199,"s":[532.926,887.982,0],"to":[0,-1.023,0],"ti":[0,1.074,0]},{"i":{"x":0.833,"y":0.831},"o":{"x":0.167,"y":0.163},"t":200,"s":[532.926,884.829,0],"to":[0,-1.074,0],"ti":[0,1.114,0]},{"i":{"x":0.833,"y":0.832},"o":{"x":0.167,"y":0.164},"t":201,"s":[532.926,881.54,0],"to":[0,-1.114,0],"ti":[0,1.143,0]},{"i":{"x":0.833,"y":0.832},"o":{"x":0.167,"y":0.165},"t":202,"s":[532.926,878.147,0],"to":[0,-1.143,0],"ti":[0,1.16,0]},{"i":{"x":0.833,"y":0.833},"o":{"x":0.167,"y":0.166},"t":203,"s":[532.926,874.684,0],"to":[0,-1.16,0],"ti":[0,1.166,0]},{"i":{"x":0.833,"y":0.834},"o":{"x":0.167,"y":0.167},"t":204,"s":[532.926,871.187,0],"to":[0,-1.166,0],"ti":[0,1.16,0]},{"i":{"x":0.833,"y":0.835},"o":{"x":0.167,"y":0.168},"t":205,"s":[532.926,867.689,0],"to":[0,-1.16,0],"ti":[0,1.143,0]},{"i":{"x":0.833,"y":0.836},"o":{"x":0.167,"y":0.168},"t":206,"s":[532.926,864.227,0],"to":[0,-1.143,0],"ti":[0,1.114,0]},{"i":{"x":0.833,"y":0.837},"o":{"x":0.167,"y":0.169},"t":207,"s":[532.926,860.834,0],"to":[0,-1.114,0],"ti":[0,1.074,0]},{"i":{"x":0.833,"y":0.838},"o":{"x":0.167,"y":0.17},"t":208,"s":[532.926,857.544,0],"to":[0,-1.074,0],"ti":[0,1.023,0]},{"i":{"x":0.833,"y":0.839},"o":{"x":0.167,"y":0.171},"t":209,"s":[532.926,854.392,0],"to":[0,-1.023,0],"ti":[0,0.962,0]},{"i":{"x":0.833,"y":0.84},"o":{"x":0.167,"y":0.173},"t":210,"s":[532.926,851.407,0],"to":[0,-0.962,0],"ti":[0,0.891,0]},{"i":{"x":0.833,"y":0.842},"o":{"x":0.167,"y":0.174},"t":211,"s":[532.926,848.621,0],"to":[0,-0.891,0],"ti":[0,0.812,0]},{"i":{"x":0.833,"y":0.843},"o":{"x":0.167,"y":0.176},"t":212,"s":[532.926,846.06,0],"to":[0,-0.812,0],"ti":[0,0.724,0]},{"i":{"x":0.833,"y":0.845},"o":{"x":0.167,"y":0.178},"t":213,"s":[532.926,843.752,0],"to":[0,-0.724,0],"ti":[0,0.629,0]},{"i":{"x":0.833,"y":0.848},"o":{"x":0.167,"y":0.181},"t":214,"s":[532.926,841.717,0],"to":[0,-0.629,0],"ti":[0,0.528,0]},{"i":{"x":0.833,"y":0.852},"o":{"x":0.167,"y":0.185},"t":215,"s":[532.926,839.978,0],"to":[0,-0.528,0],"ti":[0,0.421,0]},{"i":{"x":0.833,"y":0.859},"o":{"x":0.167,"y":0.191},"t":216,"s":[532.926,838.552,0],"to":[0,-0.421,0],"ti":[0,0.31,0]},{"i":{"x":0.833,"y":0.871},"o":{"x":0.167,"y":0.204},"t":217,"s":[532.926,837.452,0],"to":[0,-0.31,0],"ti":[0,0.196,0]},{"i":{"x":0.833,"y":0.897},"o":{"x":0.167,"y":0.236},"t":218,"s":[532.926,836.69,0],"to":[0,-0.196,0],"ti":[0,0.081,0]},{"i":{"x":0.833,"y":0.682},"o":{"x":0.167,"y":0.429},"t":219,"s":[532.926,836.273,0],"to":[0,-0.081,0],"ti":[0,-0.036,0]},{"i":{"x":0.833,"y":0.731},"o":{"x":0.167,"y":0.113},"t":220,"s":[532.926,836.206,0],"to":[0,0.036,0],"ti":[0,-0.152,0]},{"i":{"x":0.833,"y":0.788},"o":{"x":0.167,"y":0.121},"t":221,"s":[532.926,836.489,0],"to":[0,0.152,0],"ti":[0,-0.267,0]},{"i":{"x":0.833,"y":0.805},"o":{"x":0.167,"y":0.137},"t":222,"s":[532.926,837.119,0],"to":[0,0.267,0],"ti":[0,-0.379,0]},{"i":{"x":0.833,"y":0.813},"o":{"x":0.167,"y":0.145},"t":223,"s":[532.926,838.091,0],"to":[0,0.379,0],"ti":[0,-0.487,0]},{"i":{"x":0.833,"y":0.818},"o":{"x":0.167,"y":0.15},"t":224,"s":[532.926,839.394,0],"to":[0,0.487,0],"ti":[0,-0.591,0]},{"i":{"x":0.833,"y":0.821},"o":{"x":0.167,"y":0.154},"t":225,"s":[532.926,841.015,0],"to":[0,0.591,0],"ti":[0,-0.688,0]},{"i":{"x":0.833,"y":0.823},"o":{"x":0.167,"y":0.156},"t":226,"s":[532.926,842.939,0],"to":[0,0.688,0],"ti":[0,-0.779,0]},{"i":{"x":0.833,"y":0.825},"o":{"x":0.167,"y":0.158},"t":227,"s":[532.926,845.145,0],"to":[0,0.779,0],"ti":[0,-0.862,0]},{"i":{"x":0.833,"y":0.827},"o":{"x":0.167,"y":0.159},"t":228,"s":[532.926,847.612,0],"to":[0,0.862,0],"ti":[0,-0.936,0]},{"i":{"x":0.833,"y":0.828},"o":{"x":0.167,"y":0.161},"t":229,"s":[532.926,850.315,0],"to":[0,0.936,0],"ti":[0,-1.001,0]},{"i":{"x":0.833,"y":0.829},"o":{"x":0.167,"y":0.162},"t":230,"s":[532.926,853.227,0],"to":[0,1.001,0],"ti":[0,-1.055,0]},{"i":{"x":0.833,"y":0.83},"o":{"x":0.167,"y":0.163},"t":231,"s":[532.926,856.319,0],"to":[0,1.055,0],"ti":[0,-1.1,0]},{"i":{"x":0.833,"y":0.831},"o":{"x":0.167,"y":0.164},"t":232,"s":[532.926,859.559,0],"to":[0,1.1,0],"ti":[0,-1.133,0]},{"i":{"x":0.833,"y":0.832},"o":{"x":0.167,"y":0.165},"t":233,"s":[532.926,862.916,0],"to":[0,1.133,0],"ti":[0,-1.155,0]},{"i":{"x":0.833,"y":0.833},"o":{"x":0.167,"y":0.166},"t":234,"s":[532.926,866.356,0],"to":[0,1.155,0],"ti":[0,-1.165,0]},{"i":{"x":0.833,"y":0.834},"o":{"x":0.167,"y":0.166},"t":235,"s":[532.926,869.845,0],"to":[0,1.165,0],"ti":[0,-1.164,0]},{"i":{"x":0.833,"y":0.835},"o":{"x":0.167,"y":0.167},"t":236,"s":[532.926,873.347,0],"to":[0,1.164,0],"ti":[0,-1.151,0]},{"i":{"x":0.833,"y":0.836},"o":{"x":0.167,"y":0.168},"t":237,"s":[532.926,876.827,0],"to":[0,1.151,0],"ti":[0,-1.126,0]},{"i":{"x":0.833,"y":0.836},"o":{"x":0.167,"y":0.169},"t":238,"s":[532.926,880.25,0],"to":[0,1.126,0],"ti":[0,-1.09,0]},{"i":{"x":0.833,"y":0.837},"o":{"x":0.167,"y":0.17},"t":239,"s":[532.926,883.584,0],"to":[0,1.09,0],"ti":[0,-1.044,0]},{"i":{"x":0.833,"y":0.838},"o":{"x":0.167,"y":0.171},"t":240,"s":[532.926,886.792,0],"to":[0,1.044,0],"ti":[0,-0.986,0]},{"i":{"x":0.833,"y":0.84},"o":{"x":0.167,"y":0.172},"t":241,"s":[532.926,889.845,0],"to":[0,0.986,0],"ti":[0,-0.919,0]},{"i":{"x":0.833,"y":0.841},"o":{"x":0.167,"y":0.173},"t":242,"s":[532.926,892.711,0],"to":[0,0.919,0],"ti":[0,-0.843,0]},{"i":{"x":0.833,"y":0.843},"o":{"x":0.167,"y":0.175},"t":243,"s":[532.926,895.362,0],"to":[0,0.843,0],"ti":[0,-0.758,0]},{"i":{"x":0.833,"y":0.845},"o":{"x":0.167,"y":0.177},"t":244,"s":[532.926,897.77,0],"to":[0,0.758,0],"ti":[0,-0.666,0]},{"i":{"x":0.833,"y":0.847},"o":{"x":0.167,"y":0.18},"t":245,"s":[532.926,899.913,0],"to":[0,0.666,0],"ti":[0,-0.567,0]},{"i":{"x":0.833,"y":0.851},"o":{"x":0.167,"y":0.183},"t":246,"s":[532.926,901.767,0],"to":[0,0.567,0],"ti":[0,-0.463,0]},{"i":{"x":0.833,"y":0.856},"o":{"x":0.167,"y":0.189},"t":247,"s":[532.926,903.316,0],"to":[0,0.463,0],"ti":[0,-0.353,0]},{"i":{"x":0.833,"y":0.865},"o":{"x":0.167,"y":0.198},"t":248,"s":[532.926,904.543,0],"to":[0,0.353,0],"ti":[0,-0.241,0]},{"i":{"x":0.833,"y":0.886},"o":{"x":0.167,"y":0.219},"t":249,"s":[532.926,905.436,0],"to":[0,0.241,0],"ti":[0,-0.125,0]},{"i":{"x":0.833,"y":0.854},"o":{"x":0.167,"y":0.311},"t":250,"s":[532.926,905.986,0],"to":[0,0.125,0],"ti":[0,-0.009,0]},{"i":{"x":0.833,"y":0.641},"o":{"x":0.167,"y":0.195},"t":251,"s":[532.926,906.188,0],"to":[0,0.009,0],"ti":[0,0.108,0]},{"i":{"x":0.833,"y":0.776},"o":{"x":0.167,"y":0.109},"t":252,"s":[532.926,906.04,0],"to":[0,-0.108,0],"ti":[0,0.223,0]},{"i":{"x":0.833,"y":0.8},"o":{"x":0.167,"y":0.133},"t":253,"s":[532.926,905.542,0],"to":[0,-0.223,0],"ti":[0,0.336,0]},{"i":{"x":0.833,"y":0.81},"o":{"x":0.167,"y":0.143},"t":254,"s":[532.926,904.701,0],"to":[0,-0.336,0],"ti":[0,0.446,0]},{"i":{"x":0.833,"y":0.816},"o":{"x":0.167,"y":0.149},"t":255,"s":[532.926,903.524,0],"to":[0,-0.446,0],"ti":[0,0.552,0]},{"i":{"x":0.833,"y":0.82},"o":{"x":0.167,"y":0.152},"t":256,"s":[532.926,902.023,0],"to":[0,-0.552,0],"ti":[0,0.652,0]},{"i":{"x":0.833,"y":0.823},"o":{"x":0.167,"y":0.155},"t":257,"s":[532.926,900.214,0],"to":[0,-0.652,0],"ti":[0,0.745,0]},{"i":{"x":0.833,"y":0.825},"o":{"x":0.167,"y":0.157},"t":258,"s":[532.926,898.114,0],"to":[0,-0.745,0],"ti":[0,0.831,0]},{"i":{"x":0.833,"y":0.826},"o":{"x":0.167,"y":0.159},"t":259,"s":[532.926,895.744,0],"to":[0,-0.831,0],"ti":[0,0.908,0]},{"i":{"x":0.833,"y":0.828},"o":{"x":0.167,"y":0.16},"t":260,"s":[532.926,893.129,0],"to":[0,-0.908,0],"ti":[0,0.977,0]},{"i":{"x":0.833,"y":0.829},"o":{"x":0.167,"y":0.161},"t":261,"s":[532.926,890.294,0],"to":[0,-0.977,0],"ti":[0,1.036,0]},{"i":{"x":0.833,"y":0.83},"o":{"x":0.167,"y":0.162},"t":262,"s":[532.926,887.268,0],"to":[0,-1.036,0],"ti":[0,1.084,0]},{"i":{"x":0.833,"y":0.831},"o":{"x":0.167,"y":0.163},"t":263,"s":[532.926,884.081,0],"to":[0,-1.084,0],"ti":[0,1.121,0]},{"i":{"x":0.833,"y":0.832},"o":{"x":0.167,"y":0.164},"t":264,"s":[532.926,880.764,0],"to":[0,-1.121,0],"ti":[0,1.148,0]},{"i":{"x":0.833,"y":0.833},"o":{"x":0.167,"y":0.165},"t":265,"s":[532.926,877.352,0],"to":[0,-1.148,0],"ti":[0,1.162,0]},{"i":{"x":0.833,"y":0.834},"o":{"x":0.167,"y":0.166},"t":266,"s":[532.926,873.878,0],"to":[0,-1.162,0],"ti":[0,1.166,0]},{"i":{"x":0.833,"y":0.834},"o":{"x":0.167,"y":0.167},"t":267,"s":[532.926,870.378,0],"to":[0,-1.166,0],"ti":[0,1.157,0]},{"i":{"x":0.833,"y":0.835},"o":{"x":0.167,"y":0.168},"t":268,"s":[532.926,866.885,0],"to":[0,-1.157,0],"ti":[0,1.137,0]},{"i":{"x":0.833,"y":0.836},"o":{"x":0.167,"y":0.169},"t":269,"s":[532.926,863.435,0],"to":[0,-1.137,0],"ti":[0,1.105,0]},{"i":{"x":0.833,"y":0.837},"o":{"x":0.167,"y":0.17},"t":270,"s":[532.926,860.063,0],"to":[0,-1.105,0],"ti":[0,1.063,0]},{"i":{"x":0.833,"y":0.838},"o":{"x":0.167,"y":0.171},"t":271,"s":[532.926,856.803,0],"to":[0,-1.063,0],"ti":[0,1.01,0]},{"i":{"x":0.833,"y":0.839},"o":{"x":0.167,"y":0.172},"t":272,"s":[532.926,853.686,0],"to":[0,-1.01,0],"ti":[0,0.946,0]},{"i":{"x":0.833,"y":0.84},"o":{"x":0.167,"y":0.173},"t":273,"s":[532.926,850.745,0],"to":[0,-0.946,0],"ti":[0,0.874,0]},{"i":{"x":0.833,"y":0.842},"o":{"x":0.167,"y":0.174},"t":274,"s":[532.926,848.008,0],"to":[0,-0.874,0],"ti":[0,0.792,0]},{"i":{"x":0.833,"y":0.844},"o":{"x":0.167,"y":0.176},"t":275,"s":[532.926,845.504,0],"to":[0,-0.792,0],"ti":[0,0.703,0]},{"i":{"x":0.833,"y":0.846},"o":{"x":0.167,"y":0.179},"t":276,"s":[532.926,843.257,0],"to":[0,-0.703,0],"ti":[0,0.606,0]},{"i":{"x":0.833,"y":0.849},"o":{"x":0.167,"y":0.182},"t":277,"s":[532.926,841.289,0],"to":[0,-0.606,0],"ti":[0,0.503,0]},{"i":{"x":0.833,"y":0.854},"o":{"x":0.167,"y":0.186},"t":278,"s":[532.926,839.62,0],"to":[0,-0.503,0],"ti":[0,0.396,0]},{"i":{"x":0.833,"y":0.861},"o":{"x":0.167,"y":0.194},"t":279,"s":[532.926,838.268,0],"to":[0,-0.396,0],"ti":[0,0.284,0]},{"i":{"x":0.833,"y":0.876},"o":{"x":0.167,"y":0.208},"t":280,"s":[532.926,837.245,0],"to":[0,-0.284,0],"ti":[0,0.17,0]},{"i":{"x":0.833,"y":0.895},"o":{"x":0.167,"y":0.253},"t":281,"s":[532.926,836.563,0],"to":[0,-0.17,0],"ti":[0,0.054,0]},{"i":{"x":0.833,"y":0.574},"o":{"x":0.167,"y":0.4},"t":282,"s":[532.926,836.226,0],"to":[0,-0.054,0],"ti":[0,-0.063,0]},{"i":{"x":0.833,"y":0.754},"o":{"x":0.167,"y":0.104},"t":283,"s":[532.926,836.24,0],"to":[0,0.063,0],"ti":[0,-0.179,0]},{"i":{"x":0.833,"y":0.794},"o":{"x":0.167,"y":0.126},"t":284,"s":[532.926,836.604,0],"to":[0,0.179,0],"ti":[0,-0.293,0]},{"i":{"x":0.833,"y":0.807},"o":{"x":0.167,"y":0.14},"t":285,"s":[532.926,837.314,0],"to":[0,0.293,0],"ti":[0,-0.404,0]},{"i":{"x":0.833,"y":0.814},"o":{"x":0.167,"y":0.147},"t":286,"s":[532.926,838.363,0],"to":[0,0.404,0],"ti":[0,-0.512,0]},{"i":{"x":0.833,"y":0.819},"o":{"x":0.167,"y":0.151},"t":287,"s":[532.926,839.741,0],"to":[0,0.512,0],"ti":[0,-0.614,0]},{"i":{"x":0.833,"y":0.822},"o":{"x":0.167,"y":0.154},"t":288,"s":[532.926,841.433,0],"to":[0,0.614,0],"ti":[0,-0.71,0]},{"i":{"x":0.833,"y":0.824},"o":{"x":0.167,"y":0.156},"t":289,"s":[532.926,843.424,0],"to":[0,0.71,0],"ti":[0,-0.799,0]},{"i":{"x":0.833,"y":0.826},"o":{"x":0.167,"y":0.158},"t":290,"s":[532.926,845.692,0],"to":[0,0.799,0],"ti":[0,-0.88,0]},{"i":{"x":0.833,"y":0.827},"o":{"x":0.167,"y":0.16},"t":291,"s":[532.926,848.216,0],"to":[0,0.88,0],"ti":[0,-0.952,0]},{"i":{"x":0.833,"y":0.828},"o":{"x":0.167,"y":0.161},"t":292,"s":[532.926,850.97,0],"to":[0,0.952,0],"ti":[0,-1.014,0]},{"i":{"x":0.833,"y":0.83},"o":{"x":0.167,"y":0.162},"t":293,"s":[532.926,853.926,0],"to":[0,1.014,0],"ti":[0,-1.067,0]},{"i":{"x":0.833,"y":0.831},"o":{"x":0.167,"y":0.163},"t":294,"s":[532.926,857.055,0],"to":[0,1.067,0],"ti":[0,-1.108,0]},{"i":{"x":0.833,"y":0.831},"o":{"x":0.167,"y":0.164},"t":295,"s":[532.926,860.326,0],"to":[0,1.108,0],"ti":[0,-1.139,0]},{"i":{"x":0.833,"y":0.832},"o":{"x":0.167,"y":0.165},"t":296,"s":[532.926,863.705,0],"to":[0,1.139,0],"ti":[0,-1.158,0]},{"i":{"x":0.833,"y":0.833},"o":{"x":0.167,"y":0.166},"t":297,"s":[532.926,867.159,0],"to":[0,1.158,0],"ti":[0,-1.166,0]},{"i":{"x":0.833,"y":0.834},"o":{"x":0.167,"y":0.167},"t":298,"s":[532.926,870.654,0],"to":[0,1.166,0],"ti":[0,-1.162,0]},{"i":{"x":0.833,"y":0.835},"o":{"x":0.167,"y":0.167},"t":299,"s":[532.926,874.154,0],"to":[0,1.162,0],"ti":[0,-1.146,0]},{"i":{"x":0.833,"y":0.836},"o":{"x":0.167,"y":0.168},"t":300,"s":[532.926,877.624,0],"to":[0,1.146,0],"ti":[0,-1.119,0]},{"i":{"x":0.833,"y":0.837},"o":{"x":0.167,"y":0.169},"t":301,"s":[532.926,881.03,0],"to":[0,1.119,0],"ti":[0,-1.08,0]},{"i":{"x":0.833,"y":0.838},"o":{"x":0.167,"y":0.17},"t":302,"s":[532.926,884.337,0],"to":[0,1.08,0],"ti":[0,-1.031,0]},{"i":{"x":0.833,"y":0.839},"o":{"x":0.167,"y":0.171},"t":303,"s":[532.926,887.513,0],"to":[0,1.031,0],"ti":[0,-0.972,0]},{"i":{"x":0.833,"y":0.84},"o":{"x":0.167,"y":0.172},"t":304,"s":[532.926,890.525,0],"to":[0,0.972,0],"ti":[0,-0.903,0]},{"i":{"x":0.833,"y":0.841},"o":{"x":0.167,"y":0.174},"t":305,"s":[532.926,893.344,0],"to":[0,0.903,0],"ti":[0,-0.824,0]},{"i":{"x":0.833,"y":0.843},"o":{"x":0.167,"y":0.175},"t":306,"s":[532.926,895.94,0],"to":[0,0.824,0],"ti":[0,-0.738,0]},{"i":{"x":0.833,"y":0.845},"o":{"x":0.167,"y":0.178},"t":307,"s":[532.926,898.289,0],"to":[0,0.738,0],"ti":[0,-0.644,0]},{"i":{"x":0.833,"y":0.848},"o":{"x":0.167,"y":0.18},"t":308,"s":[532.926,900.367,0],"to":[0,0.644,0],"ti":[0,-0.544,0]},{"i":{"x":0.833,"y":0.852},"o":{"x":0.167,"y":0.184},"t":309,"s":[532.926,902.153,0],"to":[0,0.544,0],"ti":[0,-0.438,0]},{"i":{"x":0.833,"y":0.858},"o":{"x":0.167,"y":0.19},"t":310,"s":[532.926,903.628,0],"to":[0,0.438,0],"ti":[0,-0.328,0]},{"i":{"x":0.833,"y":0.869},"o":{"x":0.167,"y":0.201},"t":311,"s":[532.926,904.779,0],"to":[0,0.328,0],"ti":[0,-0.214,0]},{"i":{"x":0.833,"y":0.894},"o":{"x":0.167,"y":0.228},"t":312,"s":[532.926,905.594,0],"to":[0,0.214,0],"ti":[0,-0.099,0]},{"i":{"x":0.833,"y":0.769},"o":{"x":0.167,"y":0.386},"t":313,"s":[532.926,906.064,0],"to":[0,0.099,0],"ti":[0,0.018,0]},{"i":{"x":0.833,"y":0.707},"o":{"x":0.167,"y":0.13},"t":314,"s":[532.926,906.185,0],"to":[0,-0.018,0],"ti":[0,0.134,0]},{"i":{"x":0.833,"y":0.784},"o":{"x":0.167,"y":0.116},"t":315,"s":[532.926,905.956,0],"to":[0,-0.134,0],"ti":[0,0.25,0]},{"i":{"x":0.833,"y":0.803},"o":{"x":0.167,"y":0.136},"t":316,"s":[532.926,905.378,0],"to":[0,-0.25,0],"ti":[0,0.362,0]},{"i":{"x":0.833,"y":0.812},"o":{"x":0.167,"y":0.145},"t":317,"s":[532.926,904.458,0],"to":[0,-0.362,0],"ti":[0,0.471,0]},{"i":{"x":0.833,"y":0.817},"o":{"x":0.167,"y":0.15},"t":318,"s":[532.926,903.205,0],"to":[0,-0.471,0],"ti":[0,0.575,0]},{"i":{"x":0.833,"y":0.821},"o":{"x":0.167,"y":0.153},"t":319,"s":[532.926,901.632,0],"to":[0,-0.575,0],"ti":[0,0.674,0]},{"i":{"x":0.833,"y":0.823},"o":{"x":0.167,"y":0.156},"t":320,"s":[532.926,899.754,0],"to":[0,-0.674,0],"ti":[0,0.765,0]},{"i":{"x":0.833,"y":0.825},"o":{"x":0.167,"y":0.158},"t":321,"s":[532.926,897.59,0],"to":[0,-0.765,0],"ti":[0,0.849,0]},{"i":{"x":0.833,"y":0.827},"o":{"x":0.167,"y":0.159},"t":322,"s":[532.926,895.161,0],"to":[0,-0.849,0],"ti":[0,0.925,0]},{"i":{"x":0.833,"y":0.828},"o":{"x":0.167,"y":0.16},"t":323,"s":[532.926,892.493,0],"to":[0,-0.925,0],"ti":[0,0.991,0]},{"i":{"x":0.833,"y":0.829},"o":{"x":0.167,"y":0.162},"t":324,"s":[532.926,889.611,0],"to":[0,-0.991,0],"ti":[0,1.048,0]},{"i":{"x":0.833,"y":0.83},"o":{"x":0.167,"y":0.163},"t":325,"s":[532.926,886.545,0],"to":[0,-1.048,0],"ti":[0,1.094,0]},{"i":{"x":0.833,"y":0.831},"o":{"x":0.167,"y":0.164},"t":326,"s":[532.926,883.325,0],"to":[0,-1.094,0],"ti":[0,1.128,0]},{"i":{"x":0.833,"y":0.832},"o":{"x":0.167,"y":0.165},"t":327,"s":[532.926,879.984,0],"to":[0,-1.128,0],"ti":[0,1.152,0]},{"i":{"x":0.833,"y":0.833},"o":{"x":0.167,"y":0.165},"t":328,"s":[532.926,876.554,0],"to":[0,-1.152,0],"ti":[0,1.164,0]},{"i":{"x":0.833,"y":0.834},"o":{"x":0.167,"y":0.166},"t":329,"s":[532.926,873.071,0],"to":[0,-1.164,0],"ti":[0,1.165,0]},{"i":{"x":0.833,"y":0.835},"o":{"x":0.167,"y":0.167},"t":330,"s":[532.926,869.569,0],"to":[0,-1.165,0],"ti":[0,1.153,0]},{"i":{"x":0.833,"y":0.835},"o":{"x":0.167,"y":0.168},"t":331,"s":[532.926,866.083,0],"to":[0,-1.153,0],"ti":[0,1.131,0]},{"i":{"x":0.833,"y":0.836},"o":{"x":0.167,"y":0.169},"t":332,"s":[532.926,862.648,0],"to":[0,-1.131,0],"ti":[0,1.097,0]},{"i":{"x":0.833,"y":0.837},"o":{"x":0.167,"y":0.17},"t":333,"s":[532.926,859.299,0],"to":[0,-1.097,0],"ti":[0,1.051,0]},{"i":{"x":0.833,"y":0.838},"o":{"x":0.167,"y":0.171},"t":334,"s":[532.926,856.069,0],"to":[0,-1.051,0],"ti":[0,0.996,0]},{"i":{"x":0.833,"y":0.839},"o":{"x":0.167,"y":0.172},"t":335,"s":[532.926,852.99,0],"to":[0,-0.996,0],"ti":[0,0.93,0]},{"i":{"x":0.833,"y":0.841},"o":{"x":0.167,"y":0.173},"t":336,"s":[532.926,850.094,0],"to":[0,-0.93,0],"ti":[0,0.855,0]},{"i":{"x":0.833,"y":0.842},"o":{"x":0.167,"y":0.175},"t":337,"s":[532.926,847.408,0],"to":[0,-0.855,0],"ti":[0,0.772,0]},{"i":{"x":0.833,"y":0.844},"o":{"x":0.167,"y":0.177},"t":338,"s":[532.926,844.961,0],"to":[0,-0.772,0],"ti":[0,0.681,0]},{"i":{"x":0.833,"y":0.847},"o":{"x":0.167,"y":0.179},"t":339,"s":[532.926,842.776,0],"to":[0,-0.681,0],"ti":[0,0.583,0]},{"i":{"x":0.833,"y":0.85},"o":{"x":0.167,"y":0.183},"t":340,"s":[532.926,840.876,0],"to":[0,-0.583,0],"ti":[0,0.479,0]},{"i":{"x":0.833,"y":0.855},"o":{"x":0.167,"y":0.188},"t":341,"s":[532.926,839.28,0],"to":[0,-0.479,0],"ti":[0,0.37,0]},{"i":{"x":0.833,"y":0.863},"o":{"x":0.167,"y":0.196},"t":342,"s":[532.926,838.002,0],"to":[0,-0.37,0],"ti":[0,0.258,0]},{"i":{"x":0.833,"y":0.881},"o":{"x":0.167,"y":0.214},"t":343,"s":[532.926,837.057,0],"to":[0,-0.258,0],"ti":[0,0.143,0]},{"i":{"x":0.833,"y":0.88},"o":{"x":0.167,"y":0.28},"t":344,"s":[532.926,836.454,0],"to":[0,-0.143,0],"ti":[0,0.027,0]},{"i":{"x":0.833,"y":0.59},"o":{"x":0.167,"y":0.271},"t":345,"s":[532.926,836.198,0],"to":[0,-0.027,0],"ti":[0,-0.09,0]},{"i":{"x":0.833,"y":0.769},"o":{"x":0.167,"y":0.105},"t":346,"s":[532.926,836.293,0],"to":[0,0.09,0],"ti":[0,-0.206,0]},{"i":{"x":0.833,"y":0.798},"o":{"x":0.167,"y":0.13},"t":347,"s":[532.926,836.737,0],"to":[0,0.206,0],"ti":[0,-0.319,0]},{"i":{"x":0.833,"y":0.809},"o":{"x":0.167,"y":0.142},"t":348,"s":[532.926,837.526,0],"to":[0,0.319,0],"ti":[0,-0.43,0]},{"i":{"x":0.833,"y":0.815},"o":{"x":0.167,"y":0.148},"t":349,"s":[532.926,838.652,0],"to":[0,0.43,0],"ti":[0,-0.536,0]},{"i":{"x":0.833,"y":0.819},"o":{"x":0.167,"y":0.152},"t":350,"s":[532.926,840.104,0],"to":[0,0.536,0],"ti":[0,-0.637,0]},{"i":{"x":0.833,"y":0.822},"o":{"x":0.167,"y":0.155},"t":351,"s":[532.926,841.867,0],"to":[0,0.637,0],"ti":[0,-0.731,0]},{"i":{"x":0.833,"y":0.824},"o":{"x":0.167,"y":0.157},"t":352,"s":[532.926,843.924,0],"to":[0,0.731,0],"ti":[0,-0.818,0]},{"i":{"x":0.833,"y":0.826},"o":{"x":0.167,"y":0.159},"t":353,"s":[532.926,846.253,0],"to":[0,0.818,0],"ti":[0,-0.897,0]},{"i":{"x":0.833,"y":0.828},"o":{"x":0.167,"y":0.16},"t":354,"s":[532.926,848.833,0],"to":[0,0.897,0],"ti":[0,-0.967,0]},{"i":{"x":0.833,"y":0.829},"o":{"x":0.167,"y":0.161},"t":355,"s":[532.926,851.636,0],"to":[0,0.967,0],"ti":[0,-1.027,0]},{"i":{"x":0.833,"y":0.83},"o":{"x":0.167,"y":0.162},"t":356,"s":[532.926,854.635,0],"to":[0,1.027,0],"ti":[0,-1.077,0]},{"i":{"x":0.833,"y":0.831},"o":{"x":0.167,"y":0.163},"t":357,"s":[532.926,857.799,0],"to":[0,1.077,0],"ti":[0,-1.116,0]},{"i":{"x":0.833,"y":0.832},"o":{"x":0.167,"y":0.164},"t":358,"s":[532.926,861.098,0],"to":[0,1.116,0],"ti":[0,-1.144,0]},{"i":{"x":0.833,"y":0.833},"o":{"x":0.167,"y":0.165},"t":359,"s":[532.926,864.497,0],"to":[0,1.144,0],"ti":[0,-1.161,0]},{"i":{"x":0.833,"y":0.833},"o":{"x":0.167,"y":0.166},"t":360,"s":[532.926,867.964,0],"to":[0,1.161,0],"ti":[0,-1.166,0]},{"i":{"x":0.833,"y":0.834},"o":{"x":0.167,"y":0.167},"t":361,"s":[532.926,871.463,0],"to":[0,1.166,0],"ti":[0,-1.159,0]},{"i":{"x":0.833,"y":0.835},"o":{"x":0.167,"y":0.168},"t":362,"s":[532.926,874.959,0],"to":[0,1.159,0],"ti":[0,-1.141,0]},{"i":{"x":0.833,"y":0.836},"o":{"x":0.167,"y":0.168},"t":363,"s":[532.926,878.417,0],"to":[0,1.141,0],"ti":[0,-1.111,0]},{"i":{"x":0.833,"y":0.837},"o":{"x":0.167,"y":0.169},"t":364,"s":[532.926,881.804,0],"to":[0,1.111,0],"ti":[0,-1.07,0]},{"i":{"x":0.833,"y":0.838},"o":{"x":0.167,"y":0.17},"t":365,"s":[532.926,885.083,0],"to":[0,1.07,0],"ti":[0,-1.018,0]},{"i":{"x":0.833,"y":0.839},"o":{"x":0.167,"y":0.171},"t":366,"s":[532.926,888.224,0],"to":[0,1.018,0],"ti":[0,-0.957,0]},{"i":{"x":0.833,"y":0.84},"o":{"x":0.167,"y":0.173},"t":367,"s":[532.926,891.194,0],"to":[0,0.957,0],"ti":[0,-0.885,0]},{"i":{"x":0.833,"y":0.842},"o":{"x":0.167,"y":0.174},"t":368,"s":[532.926,893.964,0],"to":[0,0.885,0],"ti":[0,-0.805,0]},{"i":{"x":0.833,"y":0.843},"o":{"x":0.167,"y":0.176},"t":369,"s":[532.926,896.506,0],"to":[0,0.805,0],"ti":[0,-0.717,0]},{"i":{"x":0.833,"y":0.846},"o":{"x":0.167,"y":0.178},"t":370,"s":[532.926,898.794,0],"to":[0,0.717,0],"ti":[0,-0.621,0]},{"i":{"x":0.833,"y":0.849},"o":{"x":0.167,"y":0.181},"t":371,"s":[532.926,900.806,0],"to":[0,0.621,0],"ti":[0,-0.52,0]},{"i":{"x":0.833,"y":0.853},"o":{"x":0.167,"y":0.185},"t":372,"s":[532.926,902.522,0],"to":[0,0.52,0],"ti":[0,-0.413,0]},{"i":{"x":0.833,"y":0.86},"o":{"x":0.167,"y":0.192},"t":373,"s":[532.926,903.924,0],"to":[0,0.413,0],"ti":[0,-0.302,0]},{"i":{"x":0.833,"y":0.873},"o":{"x":0.167,"y":0.205},"t":374,"s":[532.926,904.998,0],"to":[0,0.302,0],"ti":[0,-0.188,0]},{"i":{"x":0.833,"y":0.897},"o":{"x":0.167,"y":0.241},"t":375,"s":[532.926,905.733,0],"to":[0,0.188,0],"ti":[0,-0.072,0]},{"i":{"x":0.833,"y":0.637},"o":{"x":0.167,"y":0.435},"t":376,"s":[532.926,906.123,0],"to":[0,0.072,0],"ti":[0,0.045,0]},{"i":{"x":0.833,"y":0.74},"o":{"x":0.167,"y":0.108},"t":377,"s":[532.926,906.163,0],"to":[0,-0.045,0],"ti":[0,0.161,0]},{"i":{"x":0.833,"y":0.79},"o":{"x":0.167,"y":0.123},"t":378,"s":[532.926,905.853,0],"to":[0,-0.161,0],"ti":[0,0.276,0]},{"i":{"x":0.833,"y":0.806},"o":{"x":0.167,"y":0.138},"t":379,"s":[532.926,905.196,0],"to":[0,-0.276,0],"ti":[0,0.388,0]},{"i":{"x":0.833,"y":0.813},"o":{"x":0.167,"y":0.146},"t":380,"s":[532.926,904.198,0],"to":[0,-0.388,0],"ti":[0,0.496,0]},{"i":{"x":0.833,"y":0.818},"o":{"x":0.167,"y":0.151},"t":381,"s":[532.926,902.87,0],"to":[0,-0.496,0],"ti":[0,0.599,0]},{"i":{"x":0.833,"y":0.821},"o":{"x":0.167,"y":0.154},"t":382,"s":[532.926,901.225,0],"to":[0,-0.599,0],"ti":[0,0.696,0]},{"i":{"x":0.833,"y":0.824},"o":{"x":0.167,"y":0.156},"t":383,"s":[532.926,899.279,0],"to":[0,-0.696,0],"ti":[0,0.786,0]},{"i":{"x":0.833,"y":0.825},"o":{"x":0.167,"y":0.158},"t":384,"s":[532.926,897.051,0],"to":[0,-0.786,0],"ti":[0,0.868,0]},{"i":{"x":0.833,"y":0.827},"o":{"x":0.167,"y":0.159},"t":385,"s":[532.926,894.565,0],"to":[0,-0.868,0],"ti":[0,0.941,0]},{"i":{"x":0.833,"y":0.828},"o":{"x":0.167,"y":0.161},"t":386,"s":[532.926,891.845,0],"to":[0,-0.941,0],"ti":[0,1.005,0]},{"i":{"x":0.833,"y":0.829},"o":{"x":0.167,"y":0.162},"t":387,"s":[532.926,888.918,0],"to":[0,-1.005,0],"ti":[0,1.059,0]},{"i":{"x":0.833,"y":0.83},"o":{"x":0.167,"y":0.163},"t":388,"s":[532.926,885.814,0],"to":[0,-1.059,0],"ti":[0,1.103,0]},{"i":{"x":0.833,"y":0.831},"o":{"x":0.167,"y":0.164},"t":389,"s":[532.926,882.563,0],"to":[0,-1.103,0],"ti":[0,1.135,0]},{"i":{"x":0.833,"y":0.832},"o":{"x":0.167,"y":0.165},"t":390,"s":[532.926,879.198,0],"to":[0,-1.135,0],"ti":[0,1.156,0]},{"i":{"x":0.833,"y":0.833},"o":{"x":0.167,"y":0.166},"t":391,"s":[532.926,875.753,0],"to":[0,-1.156,0],"ti":[0,1.165,0]},{"i":{"x":0.833,"y":0.834},"o":{"x":0.167,"y":0.166},"t":392,"s":[532.926,872.262,0],"to":[0,-1.165,0],"ti":[0,1.163,0]},{"i":{"x":0.833,"y":0.835},"o":{"x":0.167,"y":0.167},"t":393,"s":[532.926,868.761,0],"to":[0,-1.163,0],"ti":[0,1.149,0]},{"i":{"x":0.833,"y":0.836},"o":{"x":0.167,"y":0.168},"t":394,"s":[532.926,865.284,0],"to":[0,-1.149,0],"ti":[0,1.124,0]},{"i":{"x":0.833,"y":0.837},"o":{"x":0.167,"y":0.169},"t":395,"s":[532.926,861.866,0],"to":[0,-1.124,0],"ti":[0,1.087,0]},{"i":{"x":0.833,"y":0.837},"o":{"x":0.167,"y":0.17},"t":396,"s":[532.926,858.541,0],"to":[0,-1.087,0],"ti":[0,1.04,0]},{"i":{"x":0.833,"y":0.839},"o":{"x":0.167,"y":0.171},"t":397,"s":[532.926,855.343,0],"to":[0,-1.04,0],"ti":[0,0.982,0]},{"i":{"x":0.833,"y":0.84},"o":{"x":0.167,"y":0.172},"t":398,"s":[532.926,852.304,0],"to":[0,-0.982,0],"ti":[0,0.914,0]},{"i":{"x":0.833,"y":0.841},"o":{"x":0.167,"y":0.174},"t":399,"s":[532.926,849.454,0],"to":[0,-0.914,0],"ti":[0,0.837,0]},{"i":{"x":0.833,"y":0.843},"o":{"x":0.167,"y":0.175},"t":400,"s":[532.926,846.821,0],"to":[0,-0.837,0],"ti":[0,0.752,0]},{"i":{"x":0.833,"y":0.845},"o":{"x":0.167,"y":0.177},"t":401,"s":[532.926,844.432,0],"to":[0,-0.752,0],"ti":[0,0.659,0]},{"i":{"x":0.833,"y":0.847},"o":{"x":0.167,"y":0.18},"t":402,"s":[532.926,842.312,0],"to":[0,-0.659,0],"ti":[0,0.559,0]},{"i":{"x":0.833,"y":0.851},"o":{"x":0.167,"y":0.183},"t":403,"s":[532.926,840.48,0],"to":[0,-0.559,0],"ti":[0,0.454,0]},{"i":{"x":0.833,"y":0.857},"o":{"x":0.167,"y":0.189},"t":404,"s":[532.926,838.956,0],"to":[0,-0.454,0],"ti":[0,0.345,0]},{"i":{"x":0.833,"y":0.866},"o":{"x":0.167,"y":0.199},"t":405,"s":[532.926,837.754,0],"to":[0,-0.345,0],"ti":[0,0.232,0]},{"i":{"x":0.833,"y":0.889},"o":{"x":0.167,"y":0.221},"t":406,"s":[532.926,836.887,0],"to":[0,-0.232,0],"ti":[0,0.116,0]},{"i":{"x":0.833,"y":0.833},"o":{"x":0.167,"y":0.333},"t":407,"s":[532.926,836.364,0],"to":[0,-0.116,0],"ti":[0,0,0]},{"i":{"x":0.833,"y":0.668},"o":{"x":0.167,"y":0.166},"t":408,"s":[532.926,836.189,0],"to":[0,0,0],"ti":[0,-0.117,0]},{"i":{"x":0.833,"y":0.779},"o":{"x":0.167,"y":0.111},"t":409,"s":[532.926,836.365,0],"to":[0,0.117,0],"ti":[0,-0.232,0]},{"i":{"x":0.833,"y":0.801},"o":{"x":0.167,"y":0.134},"t":410,"s":[532.926,836.889,0],"to":[0,0.232,0],"ti":[0,-0.345,0]},{"i":{"x":0.833,"y":0.811},"o":{"x":0.167,"y":0.143},"t":411,"s":[532.926,837.757,0],"to":[0,0.345,0],"ti":[0,-0.455,0]},{"i":{"x":0.833,"y":0.817},"o":{"x":0.167,"y":0.149},"t":412,"s":[532.926,838.959,0],"to":[0,0.455,0],"ti":[0,-0.56,0]},{"i":{"x":0.833,"y":0.82},"o":{"x":0.167,"y":0.153},"t":413,"s":[532.926,840.484,0],"to":[0,0.56,0],"ti":[0,-0.659,0]},{"i":{"x":0.833,"y":0.823},"o":{"x":0.167,"y":0.155},"t":414,"s":[532.926,842.317,0],"to":[0,0.659,0],"ti":[0,-0.752,0]},{"i":{"x":0.833,"y":0.825},"o":{"x":0.167,"y":0.157},"t":415,"s":[532.926,844.439,0],"to":[0,0.752,0],"ti":[0,-0.837,0]},{"i":{"x":0.833,"y":0.826},"o":{"x":0.167,"y":0.159},"t":416,"s":[532.926,846.828,0],"to":[0,0.837,0],"ti":[0,-0.914,0]},{"i":{"x":0.833,"y":0.828},"o":{"x":0.167,"y":0.16},"t":417,"s":[532.926,849.461,0],"to":[0,0.914,0],"ti":[0,-0.982,0]},{"i":{"x":0.833,"y":0.829},"o":{"x":0.167,"y":0.161},"t":418,"s":[532.926,852.312,0],"to":[0,0.982,0],"ti":[0,-1.04,0]},{"i":{"x":0.833,"y":0.83},"o":{"x":0.167,"y":0.163},"t":419,"s":[532.926,855.352,0],"to":[0,1.04,0],"ti":[0,-1.087,0]},{"i":{"x":0.833,"y":0.831},"o":{"x":0.167,"y":0.163},"t":420,"s":[532.926,858.55,0],"to":[0,1.087,0],"ti":[0,-1.124,0]},{"i":{"x":0.833,"y":0.832},"o":{"x":0.167,"y":0.164},"t":421,"s":[532.926,861.875,0],"to":[0,1.124,0],"ti":[0,-1.149,0]},{"i":{"x":0.833,"y":0.833},"o":{"x":0.167,"y":0.165},"t":422,"s":[532.926,865.293,0],"to":[0,1.149,0],"ti":[0,-1.163,0]},{"i":{"x":0.833,"y":0.834},"o":{"x":0.167,"y":0.166},"t":423,"s":[532.926,868.771,0],"to":[0,1.163,0],"ti":[0,-1.165,0]},{"i":{"x":0.833,"y":0.834},"o":{"x":0.167,"y":0.167},"t":424,"s":[532.926,872.272,0],"to":[0,1.165,0],"ti":[0,-1.156,0]},{"i":{"x":0.833,"y":0.835},"o":{"x":0.167,"y":0.168},"t":425,"s":[532.926,875.762,0],"to":[0,1.156,0],"ti":[0,-1.135,0]},{"i":{"x":0.833,"y":0.836},"o":{"x":0.167,"y":0.169},"t":426,"s":[532.926,879.207,0],"to":[0,1.135,0],"ti":[0,-1.103,0]},{"i":{"x":0.833,"y":0.837},"o":{"x":0.167,"y":0.17},"t":427,"s":[532.926,882.572,0],"to":[0,1.103,0],"ti":[0,-1.059,0]},{"i":{"x":0.833,"y":0.838},"o":{"x":0.167,"y":0.171},"t":428,"s":[532.926,885.822,0],"to":[0,1.059,0],"ti":[0,-1.005,0]},{"i":{"x":0.833,"y":0.839},"o":{"x":0.167,"y":0.172},"t":429,"s":[532.926,888.926,0],"to":[0,1.005,0],"ti":[0,-0.941,0]},{"i":{"x":0.833,"y":0.841},"o":{"x":0.167,"y":0.173},"t":430,"s":[532.926,891.853,0],"to":[0,0.941,0],"ti":[0,-0.868,0]},{"i":{"x":0.833,"y":0.842},"o":{"x":0.167,"y":0.175},"t":431,"s":[532.926,894.572,0],"to":[0,0.868,0],"ti":[0,-0.785,0]},{"i":{"x":0.833,"y":0.844},"o":{"x":0.167,"y":0.176},"t":432,"s":[532.926,897.058,0],"to":[0,0.785,0],"ti":[0,-0.695,0]},{"i":{"x":0.833,"y":0.846},"o":{"x":0.167,"y":0.179},"t":433,"s":[532.926,899.284,0],"to":[0,0.695,0],"ti":[0,-0.598,0]},{"i":{"x":0.833,"y":0.849},"o":{"x":0.167,"y":0.182},"t":434,"s":[532.926,901.23,0],"to":[0,0.598,0],"ti":[0,-0.495,0]},{"i":{"x":0.833,"y":0.854},"o":{"x":0.167,"y":0.187},"t":435,"s":[532.926,902.874,0],"to":[0,0.495,0],"ti":[0,-0.387,0]},{"i":{"x":0.833,"y":0.862},"o":{"x":0.167,"y":0.194},"t":436,"s":[532.926,904.201,0],"to":[0,0.387,0],"ti":[0,-0.275,0]},{"i":{"x":0.833,"y":0.877},"o":{"x":0.167,"y":0.21},"t":437,"s":[532.926,905.198,0],"to":[0,0.275,0],"ti":[0,-0.161,0]},{"i":{"x":0.833,"y":0.892},"o":{"x":0.167,"y":0.26},"t":438,"s":[532.926,905.854,0],"to":[0,0.161,0],"ti":[0,-0.045,0]},{"i":{"x":0.833,"y":0.565},"o":{"x":0.167,"y":0.361},"t":439,"s":[532.926,906.163,0],"to":[0,0.045,0],"ti":[0,0.072,0]},{"i":{"x":0.833,"y":0.76},"o":{"x":0.167,"y":0.103},"t":440,"s":[532.926,906.122,0],"to":[0,-0.072,0],"ti":[0,0.188,0]},{"i":{"x":0.833,"y":0.795},"o":{"x":0.167,"y":0.128},"t":441,"s":[532.926,905.732,0],"to":[0,-0.188,0],"ti":[0,0.302,0]},{"i":{"x":0.833,"y":0.808},"o":{"x":0.167,"y":0.14},"t":442,"s":[532.926,904.995,0],"to":[0,-0.302,0],"ti":[0,0.413,0]},{"i":{"x":0.833,"y":0.815},"o":{"x":0.167,"y":0.147},"t":443,"s":[532.926,903.92,0],"to":[0,-0.413,0],"ti":[0,0.52,0]},{"i":{"x":0.833,"y":0.819},"o":{"x":0.167,"y":0.151},"t":444,"s":[532.926,902.518,0],"to":[0,-0.52,0],"ti":[0,0.622,0]},{"i":{"x":0.833,"y":0.822},"o":{"x":0.167,"y":0.154},"t":445,"s":[532.926,900.801,0],"to":[0,-0.622,0],"ti":[0,0.717,0]},{"i":{"x":0.833,"y":0.824},"o":{"x":0.167,"y":0.157},"t":446,"s":[532.926,898.788,0],"to":[0,-0.717,0],"ti":[0,0.805,0]},{"i":{"x":0.833,"y":0.826},"o":{"x":0.167,"y":0.158},"t":447,"s":[532.926,896.499,0],"to":[0,-0.805,0],"ti":[0,0.885,0]},{"i":{"x":0.833,"y":0.827},"o":{"x":0.167,"y":0.16},"t":448,"s":[532.926,893.957,0],"to":[0,-0.885,0],"ti":[0,0.957,0]},{"i":{"x":0.833,"y":0.829},"o":{"x":0.167,"y":0.161},"t":449,"s":[532.926,891.186,0],"to":[0,-0.957,0],"ti":[0,1.019,0]},{"i":{"x":0.833,"y":0.83},"o":{"x":0.167,"y":0.162},"t":450,"s":[532.926,888.216,0],"to":[0,-1.019,0],"ti":[0,1.07,0]},{"i":{"x":0.833,"y":0.831},"o":{"x":0.167,"y":0.163},"t":451,"s":[532.926,885.075,0],"to":[0,-1.07,0],"ti":[0,1.111,0]},{"i":{"x":0.833,"y":0.832},"o":{"x":0.167,"y":0.164},"t":452,"s":[532.926,881.794,0],"to":[0,-1.111,0],"ti":[0,1.141,0]},{"i":{"x":0.833,"y":0.832},"o":{"x":0.167,"y":0.165},"t":453,"s":[532.926,878.408,0],"to":[0,-1.141,0],"ti":[0,1.159,0]},{"i":{"x":0.833,"y":0.833},"o":{"x":0.167,"y":0.166},"t":454,"s":[532.926,874.95,0],"to":[0,-1.159,0],"ti":[0,1.166,0]},{"i":{"x":0.833,"y":0.834},"o":{"x":0.167,"y":0.167},"t":455,"s":[532.926,871.453,0],"to":[0,-1.166,0],"ti":[0,1.161,0]},{"i":{"x":0.833,"y":0.835},"o":{"x":0.167,"y":0.167},"t":456,"s":[532.926,867.954,0],"to":[0,-1.161,0],"ti":[0,1.144,0]},{"i":{"x":0.833,"y":0.836},"o":{"x":0.167,"y":0.168},"t":457,"s":[532.926,864.488,0],"to":[0,-1.144,0],"ti":[0,1.116,0]},{"i":{"x":0.833,"y":0.837},"o":{"x":0.167,"y":0.169},"t":458,"s":[532.926,861.089,0],"to":[0,-1.116,0],"ti":[0,1.077,0]},{"i":{"x":0.833,"y":0.838},"o":{"x":0.167,"y":0.17},"t":459,"s":[532.926,857.79,0],"to":[0,-1.077,0],"ti":[0,1.027,0]},{"i":{"x":0.833,"y":0.839},"o":{"x":0.167,"y":0.171},"t":460,"s":[532.926,854.626,0],"to":[0,-1.027,0],"ti":[0,0.967,0]},{"i":{"x":0.833,"y":0.84},"o":{"x":0.167,"y":0.172},"t":461,"s":[532.926,851.628,0],"to":[0,-0.967,0],"ti":[0,0.897,0]},{"i":{"x":0.833,"y":0.841},"o":{"x":0.167,"y":0.174},"t":462,"s":[532.926,848.825,0],"to":[0,-0.897,0],"ti":[0,0.818,0]},{"i":{"x":0.833,"y":0.843},"o":{"x":0.167,"y":0.176},"t":463,"s":[532.926,846.247,0],"to":[0,-0.818,0],"ti":[0,0.731,0]},{"i":{"x":0.833,"y":0.845},"o":{"x":0.167,"y":0.178},"t":464,"s":[532.926,843.918,0],"to":[0,-0.731,0],"ti":[0,0.636,0]},{"i":{"x":0.833,"y":0.848},"o":{"x":0.167,"y":0.181},"t":465,"s":[532.926,841.862,0],"to":[0,-0.636,0],"ti":[0,0.536,0]},{"i":{"x":0.833,"y":0.852},"o":{"x":0.167,"y":0.185},"t":466,"s":[532.926,840.1,0],"to":[0,-0.536,0],"ti":[0,0.429,0]},{"i":{"x":0.833,"y":0.858},"o":{"x":0.167,"y":0.191},"t":467,"s":[532.926,838.649,0],"to":[0,-0.429,0],"ti":[0,0.319,0]},{"i":{"x":0.833,"y":0.87},"o":{"x":0.167,"y":0.202},"t":468,"s":[532.926,837.524,0],"to":[0,-0.319,0],"ti":[0,0.205,0]},{"i":{"x":0.833,"y":0.895},"o":{"x":0.167,"y":0.232},"t":469,"s":[532.926,836.736,0],"to":[0,-0.205,0],"ti":[0,0.09,0]},{"i":{"x":0.833,"y":0.727},"o":{"x":0.167,"y":0.411},"t":470,"s":[532.926,836.292,0],"to":[0,-0.09,0],"ti":[0,-0.027,0]},{"i":{"x":0.833,"y":0.72},"o":{"x":0.167,"y":0.12},"t":471,"s":[532.926,836.199,0],"to":[0,0.027,0],"ti":[0,-0.143,0]},{"i":{"x":0.833,"y":0.786},"o":{"x":0.167,"y":0.119},"t":472,"s":[532.926,836.455,0],"to":[0,0.143,0],"ti":[0,-0.258,0]},{"i":{"x":0.833,"y":0.804},"o":{"x":0.167,"y":0.137},"t":473,"s":[532.926,837.059,0],"to":[0,0.258,0],"ti":[0,-0.371,0]},{"i":{"x":0.833,"y":0.813},"o":{"x":0.167,"y":0.145},"t":474,"s":[532.926,838.005,0],"to":[0,0.371,0],"ti":[0,-0.479,0]},{"i":{"x":0.833,"y":0.818},"o":{"x":0.167,"y":0.15},"t":475,"s":[532.926,839.283,0],"to":[0,0.479,0],"ti":[0,-0.583,0]},{"i":{"x":0.833,"y":0.821},"o":{"x":0.167,"y":0.153},"t":476,"s":[532.926,840.881,0],"to":[0,0.583,0],"ti":[0,-0.681,0]},{"i":{"x":0.833,"y":0.823},"o":{"x":0.167,"y":0.156},"t":477,"s":[532.926,842.782,0],"to":[0,0.681,0],"ti":[0,-0.772,0]},{"i":{"x":0.833,"y":0.825},"o":{"x":0.167,"y":0.158},"t":478,"s":[532.926,844.967,0],"to":[0,0.772,0],"ti":[0,-0.856,0]},{"i":{"x":0.833,"y":0.827},"o":{"x":0.167,"y":0.159},"t":479,"s":[532.926,847.415,0],"to":[0,0.856,0],"ti":[0,-0.931,0]},{"i":{"x":0.833,"y":0.828},"o":{"x":0.167,"y":0.161},"t":480,"s":[532.926,850.101,0],"to":[0,0.931,0],"ti":[0,-0.996,0]},{"i":{"x":0.833,"y":0.829},"o":{"x":0.167,"y":0.162},"t":481,"s":[532.926,852.998,0],"to":[0,0.996,0],"ti":[0,-1.052,0]},{"i":{"x":0.833,"y":0.83},"o":{"x":0.167,"y":0.163},"t":482,"s":[532.926,856.078,0],"to":[0,1.052,0],"ti":[0,-1.097,0]},{"i":{"x":0.833,"y":0.831},"o":{"x":0.167,"y":0.164},"t":483,"s":[532.926,859.308,0],"to":[0,1.097,0],"ti":[0,-1.131,0]},{"i":{"x":0.833,"y":0.832},"o":{"x":0.167,"y":0.165},"t":484,"s":[532.926,862.658,0],"to":[0,1.131,0],"ti":[0,-1.153,0]},{"i":{"x":0.833,"y":0.833},"o":{"x":0.167,"y":0.165},"t":485,"s":[532.926,866.093,0],"to":[0,1.153,0],"ti":[0,-1.165,0]},{"i":{"x":0.833,"y":0.834},"o":{"x":0.167,"y":0.166},"t":486,"s":[532.926,869.578,0],"to":[0,1.165,0],"ti":[0,-1.164,0]},{"i":{"x":0.833,"y":0.835},"o":{"x":0.167,"y":0.167},"t":487,"s":[532.926,873.08,0],"to":[0,1.164,0],"ti":[0,-1.152,0]},{"i":{"x":0.833,"y":0.835},"o":{"x":0.167,"y":0.168},"t":488,"s":[532.926,876.563,0],"to":[0,1.152,0],"ti":[0,-1.128,0]},{"i":{"x":0.833,"y":0.836},"o":{"x":0.167,"y":0.169},"t":489,"s":[532.926,879.993,0],"to":[0,1.128,0],"ti":[0,-1.093,0]},{"i":{"x":0.833,"y":0.837},"o":{"x":0.167,"y":0.17},"t":490,"s":[532.926,883.334,0],"to":[0,1.093,0],"ti":[0,-1.048,0]},{"i":{"x":0.833,"y":0.838},"o":{"x":0.167,"y":0.171},"t":491,"s":[532.926,886.553,0],"to":[0,1.048,0],"ti":[0,-0.991,0]},{"i":{"x":0.833,"y":0.84},"o":{"x":0.167,"y":0.172},"t":492,"s":[532.926,889.619,0],"to":[0,0.991,0],"ti":[0,-0.925,0]},{"i":{"x":0.833,"y":0.841},"o":{"x":0.167,"y":0.173},"t":493,"s":[532.926,892.5,0],"to":[0,0.925,0],"ti":[0,-0.849,0]},{"i":{"x":0.833,"y":0.842},"o":{"x":0.167,"y":0.175},"t":494,"s":[532.926,895.168,0],"to":[0,0.849,0],"ti":[0,-0.765,0]},{"i":{"x":0.833,"y":0.844},"o":{"x":0.167,"y":0.177},"t":495,"s":[532.926,897.596,0],"to":[0,0.765,0],"ti":[0,-0.673,0]},{"i":{"x":0.833,"y":0.847},"o":{"x":0.167,"y":0.179},"t":496,"s":[532.926,899.759,0],"to":[0,0.673,0],"ti":[0,-0.575,0]},{"i":{"x":0.833,"y":0.85},"o":{"x":0.167,"y":0.183},"t":497,"s":[532.926,901.637,0],"to":[0,0.575,0],"ti":[0,-0.471,0]},{"i":{"x":0.833,"y":0.856},"o":{"x":0.167,"y":0.188},"t":498,"s":[532.926,903.209,0],"to":[0,0.471,0],"ti":[0,-0.362,0]},{"i":{"x":0.833,"y":0.864},"o":{"x":0.167,"y":0.197},"t":499,"s":[532.926,904.461,0],"to":[0,0.362,0],"ti":[0,-0.249,0]},{"i":{"x":0.833,"y":0.884},"o":{"x":0.167,"y":0.216},"t":500,"s":[532.926,905.38,0],"to":[0,0.249,0],"ti":[0,-0.134,0]},{"i":{"x":0.833,"y":0.869},"o":{"x":0.167,"y":0.294},"t":501,"s":[532.926,905.957,0],"to":[0,0.134,0],"ti":[0,-0.018,0]},{"i":{"x":0.833,"y":0.615},"o":{"x":0.167,"y":0.229},"t":502,"s":[532.926,906.185,0],"to":[0,0.018,0],"ti":[0,0.099,0]},{"i":{"x":0.833,"y":0.772},"o":{"x":0.167,"y":0.106},"t":503,"s":[532.926,906.063,0],"to":[0,-0.099,0],"ti":[0,0.214,0]},{"i":{"x":0.833,"y":0.799},"o":{"x":0.167,"y":0.131},"t":504,"s":[532.926,905.592,0],"to":[0,-0.214,0],"ti":[0,0.328,0]},{"i":{"x":0.833,"y":0.81},"o":{"x":0.167,"y":0.142},"t":505,"s":[532.926,904.777,0],"to":[0,-0.328,0],"ti":[0,0.438,0]},{"i":{"x":0.833,"y":0.816},"o":{"x":0.167,"y":0.148},"t":506,"s":[532.926,903.625,0],"to":[0,-0.438,0],"ti":[0,0.544,0]},{"i":{"x":0.833,"y":0.82},"o":{"x":0.167,"y":0.152},"t":507,"s":[532.926,902.148,0],"to":[0,-0.544,0],"ti":[0,0.644,0]},{"i":{"x":0.833,"y":0.822},"o":{"x":0.167,"y":0.155},"t":508,"s":[532.926,900.362,0],"to":[0,-0.644,0],"ti":[0,0.738,0]},{"i":{"x":0.833,"y":0.825},"o":{"x":0.167,"y":0.157},"t":509,"s":[532.926,898.283,0],"to":[0,-0.738,0],"ti":[0,0.825,0]},{"i":{"x":0.833,"y":0.826},"o":{"x":0.167,"y":0.159},"t":510,"s":[532.926,895.934,0],"to":[0,-0.825,0],"ti":[0,0.903,0]},{"i":{"x":0.833,"y":0.828},"o":{"x":0.167,"y":0.16},"t":511,"s":[532.926,893.336,0],"to":[0,-0.903,0],"ti":[0,0.972,0]},{"i":{"x":0.833,"y":0.829},"o":{"x":0.167,"y":0.161},"t":512,"s":[532.926,890.517,0],"to":[0,-0.972,0],"ti":[0,1.031,0]},{"i":{"x":0.833,"y":0.83},"o":{"x":0.167,"y":0.162},"t":513,"s":[532.926,887.504,0],"to":[0,-1.031,0],"ti":[0,1.081,0]},{"i":{"x":0.833,"y":0.831},"o":{"x":0.167,"y":0.163},"t":514,"s":[532.926,884.328,0],"to":[0,-1.081,0],"ti":[0,1.119,0]},{"i":{"x":0.833,"y":0.832},"o":{"x":0.167,"y":0.164},"t":515,"s":[532.926,881.02,0],"to":[0,-1.119,0],"ti":[0,1.146,0]},{"i":{"x":0.833,"y":0.833},"o":{"x":0.167,"y":0.165},"t":516,"s":[532.926,877.614,0],"to":[0,-1.146,0],"ti":[0,1.162,0]},{"i":{"x":0.833,"y":0.833},"o":{"x":0.167,"y":0.166},"t":517,"s":[532.926,874.144,0],"to":[0,-1.162,0],"ti":[0,1.166,0]},{"i":{"x":0.833,"y":0.834},"o":{"x":0.167,"y":0.167},"t":518,"s":[532.926,870.644,0],"to":[0,-1.166,0],"ti":[0,1.158,0]},{"i":{"x":0.833,"y":0.835},"o":{"x":0.167,"y":0.168},"t":519,"s":[532.926,867.15,0],"to":[0,-1.158,0],"ti":[0,1.139,0]},{"i":{"x":0.833,"y":0.836},"o":{"x":0.167,"y":0.169},"t":520,"s":[532.926,863.696,0],"to":[0,-1.139,0],"ti":[0,1.108,0]},{"i":{"x":0.833,"y":0.837},"o":{"x":0.167,"y":0.169},"t":521,"s":[532.926,860.317,0],"to":[0,-1.108,0],"ti":[0,1.066,0]},{"i":{"x":0.833,"y":0.838},"o":{"x":0.167,"y":0.17},"t":522,"s":[532.926,857.046,0],"to":[0,-1.066,0],"ti":[0,1.014,0]},{"i":{"x":0.833,"y":0.839},"o":{"x":0.167,"y":0.172},"t":523,"s":[532.926,853.918,0],"to":[0,-1.014,0],"ti":[0,0.951,0]},{"i":{"x":0.833,"y":0.84},"o":{"x":0.167,"y":0.173},"t":524,"s":[532.926,850.962,0],"to":[0,-0.951,0],"ti":[0,0.879,0]},{"i":{"x":0.833,"y":0.842},"o":{"x":0.167,"y":0.174},"t":525,"s":[532.926,848.209,0],"to":[0,-0.879,0],"ti":[0,0.798,0]},{"i":{"x":0.833,"y":0.844},"o":{"x":0.167,"y":0.176},"t":526,"s":[532.926,845.686,0],"to":[0,-0.798,0],"ti":[0,0.71,0]},{"i":{"x":0.833,"y":0.846},"o":{"x":0.167,"y":0.178},"t":527,"s":[532.926,843.418,0],"to":[0,-0.71,0],"ti":[0,0.614,0]},{"i":{"x":0.833,"y":0.849},"o":{"x":0.167,"y":0.181},"t":528,"s":[532.926,841.428,0],"to":[0,-0.614,0],"ti":[0,0.511,0]},{"i":{"x":0.833,"y":0.853},"o":{"x":0.167,"y":0.186},"t":529,"s":[532.926,839.737,0],"to":[0,-0.511,0],"ti":[0,0.404,0]},{"i":{"x":0.833,"y":0.86},"o":{"x":0.167,"y":0.193},"t":530,"s":[532.926,838.36,0],"to":[0,-0.404,0],"ti":[0,0.293,0]},{"i":{"x":0.833,"y":0.874},"o":{"x":0.167,"y":0.207},"t":531,"s":[532.926,837.311,0],"to":[0,-0.293,0],"ti":[0,0.179,0]},{"i":{"x":0.833,"y":0.896},"o":{"x":0.167,"y":0.246},"t":532,"s":[532.926,836.602,0],"to":[0,-0.179,0],"ti":[0,0.063,0]},{"i":{"x":0.833,"y":0.598},"o":{"x":0.167,"y":0.426},"t":533,"s":[532.926,836.24,0],"to":[0,-0.063,0],"ti":[0,-0.054,0]},{"i":{"x":0.833,"y":0.748},"o":{"x":0.167,"y":0.105},"t":534,"s":[532.926,836.227,0],"to":[0,0.054,0],"ti":[0,-0.17,0]},{"i":{"x":0.833,"y":0.792},"o":{"x":0.167,"y":0.124},"t":535,"s":[532.926,836.564,0],"to":[0,0.17,0],"ti":[0,-0.285,0]},{"i":{"x":0.833,"y":0.807},"o":{"x":0.167,"y":0.139},"t":536,"s":[532.926,837.248,0],"to":[0,0.285,0],"ti":[0,-0.396,0]},{"i":{"x":0.833,"y":0.814},"o":{"x":0.167,"y":0.146},"t":537,"s":[532.926,838.271,0],"to":[0,0.396,0],"ti":[0,-0.504,0]},{"i":{"x":0.833,"y":0.818},"o":{"x":0.167,"y":0.151},"t":538,"s":[532.926,839.625,0],"to":[0,0.504,0],"ti":[0,-0.606,0]},{"i":{"x":0.833,"y":0.821},"o":{"x":0.167,"y":0.154},"t":539,"s":[532.926,841.294,0],"to":[0,0.606,0],"ti":[0,-0.703,0]},{"i":{"x":0.833,"y":0.824},"o":{"x":0.167,"y":0.156},"t":540,"s":[532.926,843.262,0],"to":[0,0.703,0],"ti":[0,-0.792,0]},{"i":{"x":0.833,"y":0.826},"o":{"x":0.167,"y":0.158},"t":541,"s":[532.926,845.51,0],"to":[0,0.792,0],"ti":[0,-0.874,0]},{"i":{"x":0.833,"y":0.827},"o":{"x":0.167,"y":0.16},"t":542,"s":[532.926,848.016,0],"to":[0,0.874,0],"ti":[0,-0.947,0]},{"i":{"x":0.833,"y":0.828},"o":{"x":0.167,"y":0.161},"t":543,"s":[532.926,850.753,0],"to":[0,0.947,0],"ti":[0,-1.01,0]},{"i":{"x":0.833,"y":0.829},"o":{"x":0.167,"y":0.162},"t":544,"s":[532.926,853.695,0],"to":[0,1.01,0],"ti":[0,-1.063,0]},{"i":{"x":0.833,"y":0.83},"o":{"x":0.167,"y":0.163},"t":545,"s":[532.926,856.812,0],"to":[0,1.063,0],"ti":[0,-1.106,0]},{"i":{"x":0.833,"y":0.831},"o":{"x":0.167,"y":0.164},"t":546,"s":[532.926,860.072,0],"to":[0,1.106,0],"ti":[0,-1.137,0]},{"i":{"x":0.833,"y":0.832},"o":{"x":0.167,"y":0.165},"t":547,"s":[532.926,863.445,0],"to":[0,1.137,0],"ti":[0,-1.157,0]},{"i":{"x":0.833,"y":0.833},"o":{"x":0.167,"y":0.166},"t":548,"s":[532.926,866.894,0],"to":[0,1.157,0],"ti":[0,-1.166,0]},{"i":{"x":0.833,"y":0.834},"o":{"x":0.167,"y":0.166},"t":549,"s":[532.926,870.387,0],"to":[0,1.166,0],"ti":[0,-1.162,0]},{"i":{"x":0.833,"y":0.835},"o":{"x":0.167,"y":0.167},"t":550,"s":[532.926,873.888,0],"to":[0,1.162,0],"ti":[0,-1.148,0]},{"i":{"x":0.833,"y":0.836},"o":{"x":0.167,"y":0.168},"t":551,"s":[532.926,877.362,0],"to":[0,1.148,0],"ti":[0,-1.121,0]},{"i":{"x":0.833,"y":0.837},"o":{"x":0.167,"y":0.169},"t":552,"s":[532.926,880.774,0],"to":[0,1.121,0],"ti":[0,-1.084,0]},{"i":{"x":0.833,"y":0.838},"o":{"x":0.167,"y":0.17},"t":553,"s":[532.926,884.09,0],"to":[0,1.084,0],"ti":[0,-1.035,0]},{"i":{"x":0.833,"y":0.839},"o":{"x":0.167,"y":0.171},"t":554,"s":[532.926,887.276,0],"to":[0,1.035,0],"ti":[0,-0.977,0]},{"i":{"x":0.833,"y":0.84},"o":{"x":0.167,"y":0.172},"t":555,"s":[532.926,890.302,0],"to":[0,0.977,0],"ti":[0,-0.908,0]},{"i":{"x":0.833,"y":0.841},"o":{"x":0.167,"y":0.174},"t":556,"s":[532.926,893.137,0],"to":[0,0.908,0],"ti":[0,-0.831,0]},{"i":{"x":0.833,"y":0.843},"o":{"x":0.167,"y":0.175},"t":557,"s":[532.926,895.751,0],"to":[0,0.831,0],"ti":[0,-0.745,0]},{"i":{"x":0.833,"y":0.845},"o":{"x":0.167,"y":0.177},"t":558,"s":[532.926,898.12,0],"to":[0,0.745,0],"ti":[0,-0.651,0]},{"i":{"x":0.833,"y":0.848},"o":{"x":0.167,"y":0.18},"t":559,"s":[532.926,900.219,0],"to":[0,0.651,0],"ti":[0,-0.551,0]},{"i":{"x":0.833,"y":0.851},"o":{"x":0.167,"y":0.184},"t":560,"s":[532.926,902.028,0],"to":[0,0.551,0],"ti":[0,-0.446,0]},{"i":{"x":0.833,"y":0.857},"o":{"x":0.167,"y":0.19},"t":561,"s":[532.926,903.527,0],"to":[0,0.446,0],"ti":[0,-0.336,0]},{"i":{"x":0.833,"y":0.867},"o":{"x":0.167,"y":0.2},"t":562,"s":[532.926,904.703,0],"to":[0,0.336,0],"ti":[0,-0.223,0]},{"i":{"x":0.833,"y":0.833},"o":{"x":0.167,"y":0.224},"t":563,"s":[532.926,905.544,0],"to":[0,0.223,0],"ti":[0,-0.083,0]},{"t":564.000022972191,"s":[532.926,906.04,0]}],"ix":2},"a":{"a":0,"k":[-3.723,174.31,0],"ix":1},"s":{"a":0,"k":[190,190,100],"ix":6}},"ao":0,"ef":[{"ty":28,"nm":"Set Matte","np":8,"mn":"ADBE Set Matte3","ix":1,"en":1,"ef":[{"ty":10,"nm":"Take Matte From Layer","mn":"ADBE Set Matte3-0001","ix":1,"v":{"a":0,"k":7,"ix":1}},{"ty":7,"nm":"Use For Matte","mn":"ADBE Set Matte3-0002","ix":2,"v":{"a":0,"k":4,"ix":2}},{"ty":7,"nm":"Invert Matte","mn":"ADBE Set Matte3-0003","ix":3,"v":{"a":0,"k":0,"ix":3}},{"ty":7,"nm":"If Layer Sizes Differ","mn":"ADBE Set Matte3-0004","ix":4,"v":{"a":0,"k":1,"ix":4}},{"ty":7,"nm":"Composite Matte with Original","mn":"ADBE Set Matte3-0005","ix":5,"v":{"a":0,"k":1,"ix":5}},{"ty":7,"nm":"Premultiply Matte Layer","mn":"ADBE Set Matte3-0006","ix":6,"v":{"a":0,"k":1,"ix":6}}]},{"ty":5,"nm":"AC FX [H78] Controls","np":7,"mn":"Pseudo/MHAC PrCtrl H78 5","ix":2,"en":1,"ef":[{"ty":0,"nm":"Intensity","mn":"Pseudo/MHAC PrCtrl H78 5-0001","ix":1,"v":{"a":0,"k":50,"ix":1}},{"ty":3,"nm":"XY Motion Range","mn":"Pseudo/MHAC PrCtrl H78 5-0002","ix":2,"v":{"a":0,"k":[0,70],"ix":2}},{"ty":0,"nm":"X Frequency","mn":"Pseudo/MHAC PrCtrl H78 5-0003","ix":3,"v":{"a":0,"k":3,"ix":3}},{"ty":0,"nm":"Y Frequency","mn":"Pseudo/MHAC PrCtrl H78 5-0004","ix":4,"v":{"a":0,"k":3,"ix":4}},{"ty":0,"nm":"Y Time Offset","mn":"Pseudo/MHAC PrCtrl H78 5-0005","ix":5,"v":{"a":0,"k":0,"ix":5}}]}],"shapes":[{"ty":"gr","it":[{"ty":"gr","it":[{"ty":"gr","it":[{"ind":0,"ty":"sh","ix":1,"ks":{"a":0,"k":{"i":[[0,0],[13.344,0.624],[6.334,-6.334],[12.417,3.284],[-0.417,0.908],[-3.418,-0.904],[-6.335,6.334],[-25.103,-1.173],[-11.914,-1.106],[0,0]],"o":[[-18.765,-1.938],[-25.103,-1.173],[-6.335,6.335],[-8.742,-2.312],[0.795,1.517],[12.417,3.283],[6.334,-6.335],[7.951,0.372],[0,0],[0,0]],"v":[[-20.689,7.254],[-75.952,2.478],[-147.977,22.42],[-179.884,39.781],[-185.807,30.516],[-179.884,34.412],[-147.977,17.051],[-75.952,-2.891],[-44.651,-0.477],[-20.717,1.977]],"c":true},"ix":2},"nm":"Path 1","mn":"ADBE Vector Shape - Group","hd":false},{"ty":"fl","c":{"a":0,"k":[0,0,0,1],"ix":4},"o":{"a":0,"k":100,"ix":5},"r":1,"bm":0,"nm":"Fill 1","mn":"ADBE Vector Graphic - Fill","hd":false},{"ty":"tr","p":{"a":0,"k":[0,0],"ix":2},"a":{"a":0,"k":[0,0],"ix":1},"s":{"a":0,"k":[100,100],"ix":3},"r":{"a":0,"k":0,"ix":6},"o":{"a":0,"k":10,"ix":7},"sk":{"a":0,"k":0,"ix":4},"sa":{"a":0,"k":0,"ix":5},"nm":"Transform"}],"nm":"Group 1","np":2,"cix":2,"bm":0,"ix":1,"mn":"ADBE Vector Group","hd":false},{"ty":"gr","it":[{"ind":0,"ty":"sh","ix":1,"ks":{"a":0,"k":{"i":[[5.213,-5.102],[0.235,-8.915],[4.223,-10.792],[0,0],[-9.462,-2.503],[-6.335,6.335],[-21.693,4.16],[61.77,-46.963]],"o":[[-22.053,21.585],[-0.234,8.915],[-4.223,10.793],[0,0],[12.417,3.284],[4.603,-4.603],[85.009,-21.236],[-4.981,3.766]],"v":[[-148.916,-62.04],[-172.846,-11.129],[-184.811,15.851],[-185.749,30.396],[-179.884,39.781],[-147.978,22.42],[-98.991,4.594],[-133.614,-75.261]],"c":true},"ix":2},"nm":"Path 1","mn":"ADBE Vector Shape - Group","hd":false},{"ty":"fl","c":{"a":0,"k":[0.427450984716,0.505882382393,0.549019634724,1],"ix":4},"o":{"a":0,"k":100,"ix":5},"r":1,"bm":0,"nm":"Fill 1","mn":"ADBE Vector Graphic - Fill","hd":false},{"ty":"tr","p":{"a":0,"k":[0,0],"ix":2},"a":{"a":0,"k":[0,0],"ix":1},"s":{"a":0,"k":[100,100],"ix":3},"r":{"a":0,"k":0,"ix":6},"o":{"a":0,"k":100,"ix":7},"sk":{"a":0,"k":0,"ix":4},"sa":{"a":0,"k":0,"ix":5},"nm":"Transform"}],"nm":"Group 2","np":2,"cix":2,"bm":0,"ix":2,"mn":"ADBE Vector Group","hd":false},{"ty":"gr","it":[{"ind":0,"ty":"sh","ix":1,"ks":{"a":0,"k":{"i":[[-2.816,3.284],[15.954,-2.815],[8.681,0.234],[16.657,-6.804],[16.093,-12.165],[-38.607,4.037],[-6.861,-0.321],[0,0],[-5.231,-1.311],[47.038,32.563],[2.478,1.704],[-1.407,3.91]],"o":[[2.815,-3.285],[-15.953,2.815],[-8.68,-0.235],[-12.72,5.195],[-34.168,35.008],[8.159,-1.565],[25.103,1.173],[0,0],[49.917,11.051],[-7.603,-5.219],[-7.507,-5.162],[1.408,-3.91]],"v":[[51.206,-127.73],[22.114,-130.545],[-33.253,-104.738],[-90.029,-98.639],[-133.614,-75.261],[-98.991,4.594],[-75.952,2.479],[8.977,10.455],[14.746,11.713],[50.714,-72.65],[34.783,-83.154],[31.499,-107.554]],"c":true},"ix":2},"nm":"Path 1","mn":"ADBE Vector Shape - Group","hd":false},{"ty":"fl","c":{"a":0,"k":[0.427450984716,0.505882382393,0.549019634724,1],"ix":4},"o":{"a":0,"k":100,"ix":5},"r":1,"bm":0,"nm":"Fill 1","mn":"ADBE Vector Graphic - Fill","hd":false},{"ty":"tr","p":{"a":0,"k":[0,0],"ix":2},"a":{"a":0,"k":[0,0],"ix":1},"s":{"a":0,"k":[100,100],"ix":3},"r":{"a":0,"k":0,"ix":6},"o":{"a":0,"k":100,"ix":7},"sk":{"a":0,"k":0,"ix":4},"sa":{"a":0,"k":0,"ix":5},"nm":"Transform"}],"nm":"Group 3","np":2,"cix":2,"bm":0,"ix":3,"mn":"ADBE Vector Group","hd":false},{"ty":"tr","p":{"a":0,"k":[0,0],"ix":2},"a":{"a":0,"k":[0,0],"ix":1},"s":{"a":0,"k":[100,100],"ix":3},"r":{"a":0,"k":0,"ix":6},"o":{"a":0,"k":100,"ix":7},"sk":{"a":0,"k":0,"ix":4},"sa":{"a":0,"k":0,"ix":5},"nm":"Transform"}],"nm":"Body 1","np":3,"cix":2,"bm":0,"ix":1,"mn":"ADBE Vector Group","hd":false},{"ty":"tr","p":{"a":0,"k":[0,0],"ix":2},"a":{"a":0,"k":[0,0],"ix":1},"s":{"a":0,"k":[100,100],"ix":3},"r":{"a":0,"k":0,"ix":6},"o":{"a":0,"k":100,"ix":7},"sk":{"a":0,"k":0,"ix":4},"sa":{"a":0,"k":0,"ix":5},"nm":"Transform"}],"nm":"Dolphin","np":1,"cix":2,"bm":0,"ix":1,"mn":"ADBE Vector Group","hd":false}],"ip":0,"op":565.000023012922,"st":0,"bm":0},{"ddd":0,"ind":5,"ty":4,"nm":"Tail","parent":3,"sr":1,"ks":{"o":{"a":0,"k":100,"ix":11},"r":{"a":1,"k":[{"i":{"x":[0.667],"y":[1]},"o":{"x":[0.167],"y":[0]},"t":0,"s":[4]},{"i":{"x":[0.833],"y":[1]},"o":{"x":[0.167],"y":[0]},"t":47,"s":[4]},{"i":{"x":[0.667],"y":[1]},"o":{"x":[0.333],"y":[0]},"t":57,"s":[-2]},{"i":{"x":[0.667],"y":[1]},"o":{"x":[0.167],"y":[0]},"t":67,"s":[4]},{"i":{"x":[0.667],"y":[1]},"o":{"x":[0.333],"y":[0]},"t":77,"s":[-2]},{"i":{"x":[0.667],"y":[1]},"o":{"x":[0.167],"y":[0]},"t":87,"s":[4]},{"t":94.0000038286985,"s":[4]}],"ix":10,"x":"var $bm_rt;\n$bm_rt = loopOut();"},"p":{"a":0,"k":[132.273,61.68,0],"ix":2},"a":{"a":0,"k":[132.273,61.68,0],"ix":1},"s":{"a":0,"k":[100,100,100],"ix":6}},"ao":0,"ef":[{"ty":28,"nm":"Set Matte","np":8,"mn":"ADBE Set Matte3","ix":1,"en":1,"ef":[{"ty":10,"nm":"Take Matte From Layer","mn":"ADBE Set Matte3-0001","ix":1,"v":{"a":0,"k":7,"ix":1}},{"ty":7,"nm":"Use For Matte","mn":"ADBE Set Matte3-0002","ix":2,"v":{"a":0,"k":4,"ix":2}},{"ty":7,"nm":"Invert Matte","mn":"ADBE Set Matte3-0003","ix":3,"v":{"a":0,"k":0,"ix":3}},{"ty":7,"nm":"If Layer Sizes Differ","mn":"ADBE Set Matte3-0004","ix":4,"v":{"a":0,"k":1,"ix":4}},{"ty":7,"nm":"Composite Matte with Original","mn":"ADBE Set Matte3-0005","ix":5,"v":{"a":0,"k":1,"ix":5}},{"ty":7,"nm":"Premultiply Matte Layer","mn":"ADBE Set Matte3-0006","ix":6,"v":{"a":0,"k":1,"ix":6}}]}],"shapes":[{"ty":"gr","it":[{"ty":"gr","it":[{"ind":0,"ty":"sh","ix":1,"ks":{"a":0,"k":{"i":[[7.977,14.077],[4.579,8.699],[1.418,3.649],[-11.214,-23.708],[6.912,-7.122],[-0.703,-9.384],[-10.323,7.508],[-5.161,0.939],[-1.876,1.877],[-0.939,-2.816],[-12.2,-2.815],[-2.815,0.939]],"o":[[-7.977,-14.076],[-0.739,-1.404],[-5.816,-23.05],[2.865,7.91],[-7.742,7.977],[0.704,9.385],[10.323,-7.507],[5.162,-0.939],[1.877,-1.877],[0.939,2.815],[12.199,2.816],[2.815,-0.938]],"v":[[180.711,114.387],[150.681,66.996],[147.463,59.281],[119.108,70.088],[102.352,92.803],[89.213,121.895],[101.647,121.19],[121.589,112.275],[133.319,108.443],[139.42,107.818],[159.127,118.141],[184.934,131.748]],"c":true},"ix":2},"nm":"Path 1","mn":"ADBE Vector Shape - Group","hd":false},{"ty":"fl","c":{"a":0,"k":[0.427450984716,0.505882382393,0.549019634724,1],"ix":4},"o":{"a":0,"k":100,"ix":5},"r":1,"bm":0,"nm":"Fill 1","mn":"ADBE Vector Graphic - Fill","hd":false},{"ty":"tr","p":{"a":0,"k":[0,0],"ix":2},"a":{"a":0,"k":[0,0],"ix":1},"s":{"a":0,"k":[100,100],"ix":3},"r":{"a":0,"k":0,"ix":6},"o":{"a":0,"k":100,"ix":7},"sk":{"a":0,"k":0,"ix":4},"sa":{"a":0,"k":0,"ix":5},"nm":"Transform"}],"nm":"Tail","np":2,"cix":2,"bm":0,"ix":1,"mn":"ADBE Vector Group","hd":false},{"ty":"tr","p":{"a":0,"k":[0,0],"ix":2},"a":{"a":0,"k":[0,0],"ix":1},"s":{"a":0,"k":[100,100],"ix":3},"r":{"a":0,"k":0,"ix":6},"o":{"a":0,"k":100,"ix":7},"sk":{"a":0,"k":0,"ix":4},"sa":{"a":0,"k":0,"ix":5},"nm":"Transform"}],"nm":"Dolphin","np":1,"cix":2,"bm":0,"ix":1,"mn":"ADBE Vector Group","hd":false}],"ip":0,"op":565.000023012922,"st":0,"bm":0},{"ddd":0,"ind":6,"ty":4,"nm":"Fin 2","parent":4,"sr":1,"ks":{"o":{"a":0,"k":100,"ix":11},"r":{"a":1,"k":[{"i":{"x":[0.667],"y":[1]},"o":{"x":[0.167],"y":[0]},"t":0,"s":[4]},{"i":{"x":[0.833],"y":[1]},"o":{"x":[0.167],"y":[0]},"t":46,"s":[4]},{"i":{"x":[0.667],"y":[1]},"o":{"x":[0.333],"y":[0]},"t":56,"s":[-2]},{"i":{"x":[0.667],"y":[1]},"o":{"x":[0.167],"y":[0]},"t":66,"s":[4]},{"i":{"x":[0.667],"y":[1]},"o":{"x":[0.333],"y":[0]},"t":76,"s":[-2]},{"i":{"x":[0.667],"y":[1]},"o":{"x":[0.167],"y":[0]},"t":86,"s":[4]},{"t":94.0000038286985,"s":[4]}],"ix":10,"x":"var $bm_rt;\n$bm_rt = loopOut();"},"p":{"a":0,"k":[-95.191,-9.199,0],"ix":2},"a":{"a":0,"k":[-95.191,-9.199,0],"ix":1},"s":{"a":0,"k":[100,100,100],"ix":6}},"ao":0,"ef":[{"ty":28,"nm":"Set Matte","np":8,"mn":"ADBE Set Matte3","ix":1,"en":1,"ef":[{"ty":10,"nm":"Take Matte From Layer","mn":"ADBE Set Matte3-0001","ix":1,"v":{"a":0,"k":7,"ix":1}},{"ty":7,"nm":"Use For Matte","mn":"ADBE Set Matte3-0002","ix":2,"v":{"a":0,"k":4,"ix":2}},{"ty":7,"nm":"Invert Matte","mn":"ADBE Set Matte3-0003","ix":3,"v":{"a":0,"k":0,"ix":3}},{"ty":7,"nm":"If Layer Sizes Differ","mn":"ADBE Set Matte3-0004","ix":4,"v":{"a":0,"k":1,"ix":4}},{"ty":7,"nm":"Composite Matte with Original","mn":"ADBE Set Matte3-0005","ix":5,"v":{"a":0,"k":1,"ix":5}},{"ty":7,"nm":"Premultiply Matte Layer","mn":"ADBE Set Matte3-0006","ix":6,"v":{"a":0,"k":1,"ix":6}}]}],"shapes":[{"ty":"gr","it":[{"ty":"gr","it":[{"ty":"gr","it":[{"ind":0,"ty":"sh","ix":1,"ks":{"a":0,"k":{"i":[[-0.122,-6.926],[-1.564,-5.317],[-14.389,-1.251],[3.73,12.2],[6.569,9.428]],"o":[[0.049,2.789],[1.564,5.318],[14.39,1.251],[-3.73,-12.199],[-6.569,-9.428]],"v":[[-95.19,-3.03],[-89.56,11.94],[-66.412,33.212],[-58.614,20.699],[-66.099,-3.03]],"c":true},"ix":2},"nm":"Path 1","mn":"ADBE Vector Shape - Group","hd":false},{"ty":"fl","c":{"a":0,"k":[0,0,0,1],"ix":4},"o":{"a":0,"k":100,"ix":5},"r":1,"bm":0,"nm":"Fill 1","mn":"ADBE Vector Graphic - Fill","hd":false},{"ty":"tr","p":{"a":0,"k":[0,0],"ix":2},"a":{"a":0,"k":[0,0],"ix":1},"s":{"a":0,"k":[100,100],"ix":3},"r":{"a":0,"k":0,"ix":6},"o":{"a":0,"k":20,"ix":7},"sk":{"a":0,"k":0,"ix":4},"sa":{"a":0,"k":0,"ix":5},"nm":"Transform"}],"nm":"Group 1","np":2,"cix":2,"bm":0,"ix":1,"mn":"ADBE Vector Group","hd":false},{"ty":"gr","it":[{"ind":0,"ty":"sh","ix":1,"ks":{"a":0,"k":{"i":[[-0.122,-6.926],[-1.564,-5.317],[-14.389,-1.251],[3.73,12.2],[6.569,9.428]],"o":[[0.049,2.789],[1.564,5.318],[14.39,1.251],[-3.73,-12.199],[-6.569,-9.428]],"v":[[-95.19,-3.03],[-89.56,11.94],[-66.412,33.212],[-58.614,20.699],[-66.099,-3.03]],"c":true},"ix":2},"nm":"Path 1","mn":"ADBE Vector Shape - Group","hd":false},{"ty":"fl","c":{"a":0,"k":[0.427450984716,0.505882382393,0.549019634724,1],"ix":4},"o":{"a":0,"k":100,"ix":5},"r":1,"bm":0,"nm":"Fill 1","mn":"ADBE Vector Graphic - Fill","hd":false},{"ty":"tr","p":{"a":0,"k":[0,0],"ix":2},"a":{"a":0,"k":[0,0],"ix":1},"s":{"a":0,"k":[100,100],"ix":3},"r":{"a":0,"k":0,"ix":6},"o":{"a":0,"k":100,"ix":7},"sk":{"a":0,"k":0,"ix":4},"sa":{"a":0,"k":0,"ix":5},"nm":"Transform"}],"nm":"Group 2","np":2,"cix":2,"bm":0,"ix":2,"mn":"ADBE Vector Group","hd":false},{"ty":"tr","p":{"a":0,"k":[0,0],"ix":2},"a":{"a":0,"k":[0,0],"ix":1},"s":{"a":0,"k":[100,100],"ix":3},"r":{"a":0,"k":0,"ix":6},"o":{"a":0,"k":100,"ix":7},"sk":{"a":0,"k":0,"ix":4},"sa":{"a":0,"k":0,"ix":5},"nm":"Transform"}],"nm":"Fin 2","np":2,"cix":2,"bm":0,"ix":1,"mn":"ADBE Vector Group","hd":false},{"ty":"tr","p":{"a":0,"k":[0,0],"ix":2},"a":{"a":0,"k":[0,0],"ix":1},"s":{"a":0,"k":[100,100],"ix":3},"r":{"a":0,"k":0,"ix":6},"o":{"a":0,"k":100,"ix":7},"sk":{"a":0,"k":0,"ix":4},"sa":{"a":0,"k":0,"ix":5},"nm":"Transform"}],"nm":"Dolphin","np":1,"cix":2,"bm":0,"ix":1,"mn":"ADBE Vector Group","hd":false}],"ip":0,"op":565.000023012922,"st":0,"bm":0},{"ddd":0,"ind":7,"ty":4,"nm":"Background","sr":1,"ks":{"o":{"a":0,"k":100,"ix":11},"r":{"a":0,"k":0,"ix":10},"p":{"a":0,"k":[540,540,0],"ix":2},"a":{"a":0,"k":[0,0,0],"ix":1},"s":{"a":0,"k":[190,190,100],"ix":6}},"ao":0,"shapes":[{"ty":"gr","it":[{"ind":0,"ty":"sh","ix":1,"ks":{"a":0,"k":{"i":[[0,-141.385],[141.386,0],[0,141.386],[-141.385,0]],"o":[[0,141.386],[-141.385,0],[0,-141.385],[141.386,0]],"v":[[256,0],[0,256],[-256,0],[0,-256]],"c":true},"ix":2},"nm":"Path 1","mn":"ADBE Vector Shape - Group","hd":false},{"ty":"fl","c":{"a":0,"k":[0.552941203117,0.823529422283,0.937254905701,1],"ix":4},"o":{"a":0,"k":100,"ix":5},"r":1,"bm":0,"nm":"Fill 1","mn":"ADBE Vector Graphic - Fill","hd":false},{"ty":"tr","p":{"a":0,"k":[0,0],"ix":2},"a":{"a":0,"k":[0,0],"ix":1},"s":{"a":0,"k":[100,100],"ix":3},"r":{"a":0,"k":0,"ix":6},"o":{"a":0,"k":100,"ix":7},"sk":{"a":0,"k":0,"ix":4},"sa":{"a":0,"k":0,"ix":5},"nm":"Transform"}],"nm":"Background","np":2,"cix":2,"bm":0,"ix":1,"mn":"ADBE Vector Group","hd":false}],"ip":0,"op":565.000023012922,"st":-5.00000020365417,"bm":0}],"markers":[]}